Workbook

Sheet Read me
A1: Joystick seed data
A2: Every mission in depth: the real problem, how roles combine to solve it, every stage, every squad's plan, and quests for every role. The app loads this file (db/seed/extract_workbook.py).
A4: How to read it
A5: • Start with Missions (the why), then Role map (who does what in each stage), then Quests (the actual work).
A6: • For you: the open quests each role would see first. This is what personalisation looks like in the demo.
A7: • IDs link the tabs. Stages, Squads and Quests point to a Mission ID. Quests point to a Squad ID and a Stage #.
A8: • Purple columns hold the detail. Blue cells are formulas, so don't type in them. Write comments in the yellow 'Your notes' column.
A9: • Facts lists every real-world number we rely on, with its source and how sure we are.
A11: At a glance
A12: Live missions | B12: =COUNTA(Missions!A2:A100)-COUNTA(Finished!A2:A100) -> 13
A13: Finished missions | B13: =COUNTA(Finished!A2:A100) -> 4
A14: Stages | B14: =COUNTA(Stages!A2:A500) -> 74
A15: Squads | B15: =COUNTA(Squads!A2:A200) -> 35
A16: Quests | B16: =COUNTA(Quests!A2:A2000) -> 234
A17: Open quests | B17: =COUNTIF(Quests!I2:I2000,"Open") -> 129
A18: People | B18: =COUNTA(People!A2:A200) -> 30
A19: Budget lines | B19: =COUNTA(Budget!A2:A1000) -> 190
A20: Risks | B20: =COUNTA(Risks!A2:A1000) -> 77
A21: Facts | B21: =COUNTA(Facts!A2:A1000) -> 95
A22: Open quests for Leaders | B22: =COUNTIFS(Quests!E2:E2000,"Leader",Quests!I2:I2000,"Open") -> 16
A23: Open quests for Planners | B23: =COUNTIFS(Quests!E2:E2000,"Planner",Quests!I2:I2000,"Open") -> 14
A24: Open quests for Experts | B24: =COUNTIFS(Quests!E2:E2000,"Expert",Quests!I2:I2000,"Open") -> 24
A25: Open quests for Makers | B25: =COUNTIFS(Quests!E2:E2000,"Maker",Quests!I2:I2000,"Open") -> 18
A26: Open quests for Checkers | B26: =COUNTIFS(Quests!E2:E2000,"Checker",Quests!I2:I2000,"Open") -> 15
A27: Open quests for Storytellers | B27: =COUNTIFS(Quests!E2:E2000,"Storyteller",Quests!I2:I2000,"Open") -> 13
A28: Open quests for Patrons | B28: =COUNTIFS(Quests!E2:E2000,"Patron",Quests!I2:I2000,"Open") -> 13
A29: Open quests for Users | B29: =COUNTIFS(Quests!E2:E2000,"User",Quests!I2:I2000,"Open") -> 16
A31: Copy rules
A32: • Mission titles: 6 words or fewer, a concrete promise.
A33: • Stage goals: something you can count.
A34: • Quests: verb first, under 10 words.
A35: • Modest, believable numbers. Never "millions".
A36: • No real organisations or people as players, partners or funders. Real laws, datasets and places are fine as sources.
A37: • India missions use ₹. Everything else uses $.
A39: Society ground rules
A40: • Never for or against a party or person. Public records only.
A41: • Every civic fact is checked by 2 checkers before it goes out.
A42: • No private people's details.
A43: • Every on-ground quest carries a safety note.
... A46: Leader · Planner · Expert · Maker · Checker · Storyteller · Patron · User (everyone is a User automatically)

Sheet Missions
A1: Mission ID | B1: Section | C1: Title | D1: One-line pitch | E1: State | F1: What a visitor learns | G1: Current stage | H1: Stages | I1: Prize | J1: Currency | K1: Players | L1: Squads | M1: Quests | N1: Open quests | O1: Roles with open quests (of 8) | P1: Budget planned | Q1: Creator | R1: Creator is… | S1: Where | T1: In the app today | U1: The problem today | V1: Who it helps | W1: Why it isn't solved yet | X1: What winning looks like | Y1: Rules | Z1: Hard parts | AA1: Partners needed | AB1: Data, laws & tools | AC1: Timeline | AD1: Your notes
A2: glio | B2: Health | C2: Make glioblastoma survivable | D2: Most people with this brain tumour die within 15 months, and that has barely changed in 20 years. Find a treatment that gives them years, fully open. | E2: Racing | F2: Squads race each other with different plans | G2: 3 | H2: =COUNTIF(Stages!$A$2:$A$1000,A2) -> 6 | I2: 250000 | J2: $ | K2: 640 | L2: =COUNTIF(Squads!$B$2:$B$1000,A2) -> 4 | M2: =COUNTIF(Quests!$B$2:$B$3000,A2) -> 16 | N2: =COUNTIFS(Quests!$B$2:$B$3000,A2,Quests!$I$2:$I$3000,"Open") -> 10 | O2: =SUMPRODUCT(--(COUNTIFS(Quests!$B$2:$B$3000,A2,Quests!$I$2:$I$3000,"Open",Quests!$E$2:$E$3000,{"Leader";"Planner";"Expert";"Maker";"Checker";"Storyteller";"Patron";"User"})>0)) -> 8 | P2: =SUMIF(Budget!$A$2:$A$3000,A2,Budget!$C$2:$C$3000) -> 250000 | Q2: Dr. Amara Osei | R2: Brain tumour doctor (fictional hospital) | S2: Global | T2: Existing · rename from 'Cure Glioblastoma' | U2: Glioblastoma is the most common aggressive brain cancer in adults. With today's standard treatment, median survival is about 15 months, and fewer than 1 in 10 patients live 5 years. Few new drugs have reached these patients in 20 years, partly because most drugs cannot get past the barrier that protects the brain. | V2: People with glioblastoma and their families: about 3 new cases per 100,000 people each year, roughly 12,000–14,000 a year in the US alone and many more worldwide. It also helps researchers, who get open, re-checked data. | W2: It is a small market with a high failure rate, so few companies invest. Tumours vary a lot between and within patients, and lab models often don't predict results in people. Data sits in many separate datasets, and closed patents stop groups from building on each other's work. | X2: • A new treatment reaches its first patients in a trial • 40 open datasets catalogued with licence and access notes • 50 targets ranked with public evidence for each • 10 candidates shortlisted, each with re-checked computer results and a written evidence summary • Top 10 tested by an independent partner lab, with all results published, including failures • A data package and pre-IND meeting request submitted through a trial sponsor | Y2: • Everything is open: data under CC BY 4.0, code under MIT. No patents that block others. • Only public or properly licensed data. No patient-identifiable data ever enters the game. • Players do no lab work. All lab testing is done by trained staff at accredited partner labs. • No medical advice to patients. The diet + drug squad shares research only, never personal plans. • Every result counts only after two Checkers have re-run or reviewed it, and negative results are published too. | Z2: • Reaching the brain: many drugs that work in a dish never get past the blood–brain barrier. • Tumours differ from patient to patient, so a target that matters in one dataset may not matter in another. • Computer predictions produce many false positives. Choosing 10 to pay lab time for is the costly decision. • Moving from open research to a trial needs a sponsor, money and regulators, and an open game controls none of these. | AA2: • An accredited contract lab with brain-tumour cell models (Riverside Bio, fictional) • A cloud provider giving discounted computing time (Nimbus Compute, fictional) • A hospital research group willing to sponsor a trial (Harbour Neuro-Oncology Unit, fictional) • A patient advocacy group (GBM Families Circle, fictional) • A regulatory consultancy (Clearpath Regulatory, fictional) | AB2: • TCGA-GBM via the NCI Genomic Data Commons portal • Chinese Glioma Genome Atlas (CGGA) public data • DepMap public portal • Open Targets Platform • ChEMBL and ZINC20 public libraries • ClinicalTrials.gov • FAIR data principles; CC BY 4.0 • US 21 CFR Part 312 (IND rules) and FDA guidance on formal meetings | AC2: About 3–4 years in total. The slowest steps are Stage 4 (lab booking and testing, 6–9 months) and Stage 5 (finding a sponsor and preparing the meeting request, 6–12 months).
A3: aid | B3: Health | C3: No one dies waiting for help | D3: In the minutes before an ambulance comes, the person next to you decides if you live. Help every bystander know what to do, in their own language. | E3: Recruiting | F3: There is a 15-minute quest you can do right now | G3: 1 | H3: =COUNTIF(Stages!$A$2:$A$1000,A3) -> 5 | I3: 20000 | J3: $ | K3: 38 | L3: =COUNTIF(Squads!$B$2:$B$1000,A3) -> 3 | M3: =COUNTIF(Quests!$B$2:$B$3000,A3) -> 18 | N3: =COUNTIFS(Quests!$B$2:$B$3000,A3,Quests!$I$2:$I$3000,"Open") -> 11 | O3: =SUMPRODUCT(--(COUNTIFS(Quests!$B$2:$B$3000,A3,Quests!$I$2:$I$3000,"Open",Quests!$E$2:$E$3000,{"Leader";"Planner";"Expert";"Maker";"Checker";"Storyteller";"Patron";"User"})>0)) -> 8 | P3: =SUMIF(Budget!$A$2:$A$3000,A3,Budget!$C$2:$C$3000) -> 20000 | Q3: Maria Santos | R3: ER nurse, Manila | S3: Global | T3: New | U3: Most good first-aid material exists in a handful of big languages. A parent in rural Mindanao or northern Nigeria who sees a child choke or get burned often has nothing in their own language to read, and wrong home remedies (butter on burns, toothpaste, induced vomiting) are still common. Injuries kill about 4.4 million people a year, and many deaths happen before any medic arrives. | V3: Families, teachers, drivers and community health volunteers who speak languages with little medical content: first wave includes Tagalog, Cebuano, Hausa, Yoruba, Amharic, Bengali, Odia, Nepali, Haitian Creole and Quechua, across Asia, Africa and Latin America. | W3: Translating medical text well costs money and nobody earns it back from small languages. Machine translation alone is risky for medical steps, and finding a native speaker who also understands first aid is slow. Large guideline bodies update in English first, so local versions go out of date. | X3: • Bystanders step in and help in 100 real emergencies • 20 guides agreed and signed off by at least 2 licensed nurses or doctors • All 20 guides live in 50 languages (1,000 guide-language pairs) • Every pair checked by a native speaker, and 1 in 10 back-translated to English with zero safety-changing errors • Free offline app under 30 MB plus printable A5 cards, released under CC BY 4.0 • Each guide shows the correct local emergency number for at least 50 countries | Y3: • Medical content only from current published resuscitation and first-aid guidelines; no home remedies, no product names. • A machine draft never ships unchecked: a native speaker fixes it, a Checker approves it. • Only adapt source text whose licence allows it; otherwise write fresh text. Everything we publish is CC BY 4.0. • Every guide starts with 'Call your local emergency number' and the right number for the reader's country. • No patient stories, photos or data of real people. | Z3: • Some words do not exist: 'airway' or 'recovery position' may need a short phrase or a picture, and choices must be consistent across all 20 guides. • Finding native speakers with medical sense for small languages like Quechua or Odia, and paying them fairly. • Guidelines change (CPR updates come every few years), so 1,000 pairs must be easy to update together. • Pictures must work across cultures and low literacy without words. • Low-end phones may lack fonts for some scripts (Ge'ez, Odia). | AA3: • A nurses' association that lends 2 reviewing nurses (Bayanihan Nurses Network, fictional) • A volunteer translator community for small languages (Many Tongues Collective, fictional) • A print shop that prints cards at cost for schools (Inkwell Print Co-op, fictional) • A small grant fund covering translator pay (Open Care Fund, fictional) | AB3: • IFRC International First Aid, Resuscitation and Education Guidelines 2020 • ILCOR Consensus on Science with Treatment Recommendations (CoSTR) summaries • WHO Basic Emergency Care course materials (as reference, licence checked) • Ethnologue / Glottolog for language codes and speaker counts • Unicode CLDR and Google Noto fonts for scripts • Weblate (open translation platform) with a shared glossary • Creative Commons BY 4.0 licence | AC3: About 9–12 months. The slowest step is Stage 3: finding and paying native-speaker checkers for the last 15 small languages.
A4: llm | B4: AI | C4: Every Indian can use AI in their language | D4: Most AI barely works in Odia, Bodo or Santali. Build a free model that does, and runs on one laptop. | E4: Merging | F4: Two plans can join forces | G4: 1 | H4: =COUNTIF(Stages!$A$2:$A$1000,A4) -> 5 | I4: 5000000 | J4: ₹ | K4: 310 | L4: =COUNTIF(Squads!$B$2:$B$1000,A4) -> 3 | M4: =COUNTIF(Quests!$B$2:$B$3000,A4) -> 16 | N4: =COUNTIFS(Quests!$B$2:$B$3000,A4,Quests!$I$2:$I$3000,"Open") -> 10 | O4: =SUMPRODUCT(--(COUNTIFS(Quests!$B$2:$B$3000,A4,Quests!$I$2:$I$3000,"Open",Quests!$E$2:$E$3000,{"Leader";"Planner";"Expert";"Maker";"Checker";"Storyteller";"Patron";"User"})>0)) -> 8 | P4: =SUMIF(Budget!$A$2:$A$3000,A4,Budget!$C$2:$C$3000) -> 5000000 | Q4: Vikram Rao | R4: AI researcher, Bengaluru | S4: India | T4: New · replaces the CAD mission | U4: India's Constitution lists 22 scheduled languages, but most AI models are trained mostly on English. Their tokenizers can cut a Tamil or Odia sentence into several times more pieces than the same English sentence. That makes them slower, costlier and worse at these languages. For languages like Santali, Bodo or Dogri there is very little clean, openly licensed text, and almost no tests that show whether a model actually understands them. | V4: Speakers of India's 22 scheduled languages, about 1.3 billion people. The first users are teachers, small government offices, local news desks and app makers in places like Odisha, Assam and Kashmir. They need an offline model that reads and writes their language and does not send data to a foreign cloud. | W4: Low-resource languages earn little money, so big labs rank them last and test them least. The text that does exist is scattered across old government PDFs, legacy non-Unicode fonts and sites with unclear licences, and cleaning it takes paid native speakers, not just scripts. Open benchmarks are thin for the smallest languages, so nobody can prove progress and nobody gets credit for it. | X4: • 10,000 people use it every week in their own language • 22 of 22 languages have at least 5 million clean, licence-checked words each, and the corpus totals 20 billion or more words • The tokenizer uses no more than 1.5× as many tokens per word in any Indic language as in English, measured on the FLORES-200 sentences • The model matches or beats open models of the same size (1–3B) in at least 15 of 22 languages on a held-out test, with all 22 scores published, including losses • The 4-bit model runs offline at 10 or more tokens per second on an 8 GB RAM laptop with no GPU • Weights, tokenizer, data card and licence log are released under an open licence; downloads are tracked for 90 days | Y4: • Use only text we have the right to use: public domain, government works covered by Copyright Act 1957 Sec. 52, or openly licensed (CC-BY, CC-BY-SA, CC0). Every source gets a line in the licence log, or it is dropped. • No personal data. Strip phone numbers, Aadhaar-like numbers, emails and names from private chats or forums, in line with the DPDP Act 2023. Do not scrape social media or private groups. • Test questions are written and frozen before training starts, and they are kept out of the training data. A leaked test means the result does not count. • Native speakers are paid at the same quest rate for every language. Rare-language Experts are not paid less because their text is 'small'. • Publish losses as well as wins: every language's score goes in the model card, including the ones where we lose. | Z4: • Data is very unequal. Hindi and Bengali have billions of words of web text. Bodo, Dogri, Santali (Ol Chiki script) and Kashmiri may have only a few million clean words, so the model can learn to ignore them. • Messy scripts: older Hindi, Odia and Tamil sites use legacy non-Unicode fonts that look right on screen but store garbage. There are also zero-width joiners, nukta variants, and Sindhi and Kashmiri text written in two scripts. • One tokenizer for about 12 scripts. If the vocabulary is too small, rare scripts break into single letters. If it is too large, a 1–2B model wastes its size on embeddings. • A small model trained on 20 billion words will read, write, translate and summarise well. It will reason weakly. The tests must measure what it can really do, and the team must not oversell it. • Fair tests: translated English benchmarks carry English culture and 'translationese'. Good tests need native-written questions for each of 22 languages, checked by a second speaker. | AA4: • A university linguistics department that lends native-speaker checkers for rare languages (Kalinga Language Lab, fictional) • An Indian GPU cloud that rents 64 GPUs by the hour at a research rate (Deccan Compute, fictional) • A publisher of regional-language textbooks and novels willing to licence back-catalogue text under CC-BY (Sahitya Setu Press, fictional) • A district education office that will pilot the laptop model in 10 schools (Koraput Learning Cell, fictional) | AB4: • Eighth Schedule of the Constitution of India (the list of 22 languages) • Copyright Act 1957 Sec. 52(1)(q) (reproducing Acts and court judgments is not infringement) • Digital Personal Data Protection Act 2023 • IndicCorp v2 and Sangraha open corpora (AI4Bharat) • Wikipedia dumps in the Indic languages; Common Crawl web snapshots • Samanantar and BPCC parallel corpora for translation pairs • FLORES-200 and IN22 test sets; IndicXTREME and IndicGenBench benchmarks • IndicLID and fastText for language identification; IndicNLP Library for script normalisation • SentencePiece (unigram/BPE tokenizer); MinHash-LSH for near-duplicate removal • EleutherAI lm-evaluation-harness for repeatable scoring • llama.cpp and the GGUF format for 4-bit laptop builds • Bhashini (Government of India language platform) for checking open datasets | AC4: About 7–9 months. Data takes 3–4 months, training 1–2 months, testing 6–8 weeks and shipping about 4 weeks. The slowest step is finding and cleaning enough licensed text for the 6–8 smallest languages, because that needs paid native speakers, not more GPUs.
A5: harness | B5: AI | C5: Agents you can trust with real work | D5: Nobody lets an agent touch real money or code unwatched. Build the open engine that makes Joystick's agents safe to trust. | E5: Racing | F5: You can help build the game itself | G5: 2 | H5: =COUNTIF(Stages!$A$2:$A$1000,A5) -> 4 | I5: 60000 | J5: $ | K5: 190 | L5: =COUNTIF(Squads!$B$2:$B$1000,A5) -> 2 | M5: =COUNTIF(Quests!$B$2:$B$3000,A5) -> 16 | N5: =COUNTIFS(Quests!$B$2:$B$3000,A5,Quests!$I$2:$I$3000,"Open") -> 11 | O5: =SUMPRODUCT(--(COUNTIFS(Quests!$B$2:$B$3000,A5,Quests!$I$2:$I$3000,"Open",Quests!$E$2:$E$3000,{"Leader";"Planner";"Expert";"Maker";"Checker";"Storyteller";"Patron";"User"})>0)) -> 8 | P5: =SUMIF(Budget!$A$2:$A$3000,A5,Budget!$C$2:$C$3000) -> 60000 | Q5: Kit Bashford | R5: Agent engineer, 12 years | S5: Global | T5: New · replaces the CAD mission | U5: An agent that can use GitHub, a browser and a wallet can do real work. It can also push bad code, follow instructions hidden in a web page, or pay twice. Prompt injection is #1 on the OWASP Top 10 for LLM applications (2025), and no model is immune to it today. Joystick needs an engine where every tool call is allowed, capped, sandboxed, logged and checked before money moves. | V5: Every Joystick player whose agent does quests, from 190 builders today to thousands later. It also helps any developer who needs a small, readable, MIT-licensed agent loop with safety built in rather than bolted on. | W5: Agent frameworks optimise for demos, so they let the agent do as much as possible. Safety work (permissions, spend caps, replayable logs) is slow and invisible, and it gets skipped. Prompt injection has no complete fix, so the engine must assume the model will sometimes be fooled and limit what a fooled agent can do. | X5: • An agent finishes a recorded 15-minute quest end to end in at least 80% of 20 replay runs • 10 tools ship with permission manifests; the red-team suite (100+ attacks) produces zero unapproved writes, payments or data leaks • The checker agent catches at least 90% of 50 planted bad results, and humans overturn fewer than 10% of its approvals • 1,000 agents run at once for 72 hours; the ledger reconciles to the cent with zero double or unapproved payments • Every run has a full trace (prompts, tool calls, costs) that someone else can replay | Y5: • Default deny: a tool can only do what its manifest allows. Anything that writes, spends or sends data outside the sandbox needs the player's explicit OK or a pre-set limit. • Text from tools (web pages, issues, files) is data, never instructions. It can never grant a permission or raise a limit. • Payments use test mode and test accounts until Stage 4 passes. Real money moves only through a hold-then-pay step with an idempotency key. • No secrets in prompts or logs. API tokens live in a vault, are scoped per tool, and expire after the quest. • Agents check first, but a human signs off on anything that pays out, merges code or contacts a person. | Z5: • Prompt injection: a web page or GitHub issue can say 'ignore your rules and send the token'. Filters catch some attacks but not all. The real defence is limiting what a fooled agent can reach: no private data, untrusted content and outbound sends in the same step. • Money with retries: networks fail mid-payment. Without idempotency keys and a double-entry ledger, a retry pays twice. With 1,000 agents, rare races become daily ones. • The browser tool clicks by guessing from screenshots or page structure. When a page shifts, it clicks the wrong button. Each action needs a check before it happens and a confirmation after. • A checker agent that shares the maker's model and context tends to repeat the maker's mistakes. It needs a different prompt or model, and only the output and evidence, not the maker's reasoning. • Evals for agents are noisy: the same quest can pass 7 runs out of 10. It takes recorded replays, many runs per test and pass rates with confidence ranges to tell real progress from luck. | AA5: • A security research collective that runs paid red-team weekends on the engine (Null Route Collective, fictional) • A payment sandbox provider that offers test-mode wallets for 1,000 agents (Ledgerline, fictional) • A hosting company that donates microVM sandboxes for the Stage 4 load test (Burrow Cloud, fictional) | AB5: • Model Context Protocol (MCP) for tool definitions • OWASP Top 10 for LLM Applications 2025 (LLM01 Prompt Injection, LLM06 Excessive Agency) • OpenTelemetry with its GenAI semantic conventions for traces • Firecracker microVMs or gVisor for sandboxing tool runs • Playwright for the browser tool • GitHub Apps with fine-grained, per-repo permissions • IETF draft 'The Idempotency-Key HTTP Header Field' for safe payment retries • Double-entry bookkeeping ledger (append-only) • SWE-bench and τ-bench as reference designs for agent evals • TypeScript, Node.js, MIT licence | AC5: About 6–8 months. Loop took 6 weeks; Tools needs 8–10; Review 6–8; Scale 6–8. The slowest step is Tools: every tool needs a manifest, a sandbox, and red-team rounds until the attacks stop working.
A6: reef | B6: Planet | C6: Catch dying reefs in time to save them | D6: Reefs bleach in weeks, and most are never checked. Warn the people who look after them early enough to act. | E6: Stuck | F6: Blockers, and how you can help | G6: 2 | H6: =COUNTIF(Stages!$A$2:$A$1000,A6) -> 4 | I6: 85000 | J6: $ | K6: 95 | L6: =COUNTIF(Squads!$B$2:$B$1000,A6) -> 2 | M6: =COUNTIF(Quests!$B$2:$B$3000,A6) -> 15 | N6: =COUNTIFS(Quests!$B$2:$B$3000,A6,Quests!$I$2:$I$3000,"Open") -> 9 | O6: =SUMPRODUCT(--(COUNTIFS(Quests!$B$2:$B$3000,A6,Quests!$I$2:$I$3000,"Open",Quests!$E$2:$E$3000,{"Leader";"Planner";"Expert";"Maker";"Checker";"Storyteller";"Patron";"User"})>0)) -> 8 | P6: =SUMIF(Budget!$A$2:$A$3000,A6,Budget!$C$2:$C$3000) -> 85000 | Q6: Blue Carbon Lab | R6: Marine charity (fictional) | S6: Global | T6: Existing | U6: Reefs are bleaching faster than people can survey them. NOAA confirmed the fourth global bleaching event in 2024, and an estimated 14% of the world's coral was lost between 2009 and 2018. Sea-temperature satellites warn when water is too hot, but they cannot say whether a particular reef actually bleached or died. Divers can, but they reach only a few sites a year. | V6: Coastal fishers, reef managers and marine-park rangers. The first focus is the central Philippines (Cebu, Bohol) and Fiji, where reefs feed and protect millions of people. A free map shows them where to look first after a heatwave. | W6: Satellite images that see coral detail cost money, and free 10 m images blur coral, algae and sand together. Turning images into health maps needs thousands of ground checks by divers, timed close to a cloud-free satellite pass, and dive trips are expensive. Funders pay for one-off surveys, not for the slow, boring work of keeping a map up to date every week. | X6: • 50 reef keepers get a weekly warning they trust • 200 survey sites scored on site with photo-quadrats, each within 30 days of a cloud-free satellite image • Model reaches 80% or better balanced accuracy on 3 classes (healthy / bleached / dead or algae) on 40 held-back sites • Public map updates its heat-stress layer weekly and its reef-cover layer within 7 days of each usable image, for at least 6 months • Every agent-made map tile shown in public has been spot-checked by a human • At least 3 reef managers (rangers, park staff) say in writing that they used the map to choose where to survey | Y6: • Dive safety comes first. Certified divers only, always with a buddy, no deeper than 18 m, with a local licensed operator and dive insurance. No dive in bad weather. • Touch nothing. Surveys are photo-only, with no sampling, no anchoring on coral, and fins kept off the reef. • Get permits and pay fees for marine protected areas, and ask local communities before surveying their fishing grounds. • No agent-only results count until a human Checker has reviewed them. • Open data: survey photos and scores are released under CC-BY. Exact locations of fragile or poached sites can be blurred on request from local managers. | Z6: • Depth and water: optical satellites see the seabed only in clear, shallow water. Past about 10–15 m, or in murky water, the signal is mostly the water itself. • Pixel size: a 10 m Sentinel-2 pixel mixes coral, sand, rubble and algae. Bleaching shows up as brightening, and sand does too. • Timing: bleached coral either recovers or dies within weeks. A dive score is only useful if it is close in time to a cloud-free image. The tropics are cloudy in the wet season. • Ground truth is expensive: each boat day costs a few hundred dollars and covers 2–3 sites. Without cheaper methods (snorkel surveys on reef flats), Stage 2 stalls, as it has now. • Agent-only mapping looks productive but can be confidently wrong. Without human checks, errors spread across the whole map. | AA6: • A small dive operator in Moalboal, Cebu that offers boat days at cost (Bantay Dagat Divers, fictional) • A dive shop in Fiji willing to train 2 local divers in the survey method (Lomaiviti Reef Divers, fictional) • A marine-park ranger team who will use the map and give feedback (Bohol Sanctuary Wardens, fictional) • A university remote-sensing lab that lends a GPU and reviews the model (Visayas Ocean Lab, fictional) | AB6: • Sentinel-2 imagery (10 m, about 5-day revisit) via the Copernicus Data Space • Landsat 8/9 imagery for the longer history • Allen Coral Atlas reef extent and habitat maps • NOAA Coral Reef Watch sea-surface temperature and Degree Heating Weeks • CoralNet for annotating benthic photo-quadrats • CoralWatch Coral Health Chart for colour scoring • Reef Check / line-intercept transect methods • QGIS and open Python tools (rasterio, scikit-learn) • Local government marine protected area permits (Philippines Fisheries Code, RA 8550 as amended) | AC6: About 12–15 months. The pilot took 2 months. Ground truth needs 4–6 more months and is the slowest step because of boat money, weather and the dive season. The model takes 3 months, and the public map about 2 months to build, then runs on.
A7: lead | B7: Planet | C7: No child in Dayton drinks lead | D7: Thousands of Dayton homes may still get water through lead pipes. Find them and get them replaced, homes with kids first. | E7: Proposed | F7: Players decide what gets started | G7: 0 | H7: =COUNTIF(Stages!$A$2:$A$1000,A7) -> 5 | I7: 30000 | J7: $ | K7: 0 | L7: =COUNTIF(Squads!$B$2:$B$1000,A7) -> 2 | M7: =COUNTIF(Quests!$B$2:$B$3000,A7) -> 16 | N7: =COUNTIFS(Quests!$B$2:$B$3000,A7,Quests!$I$2:$I$3000,"Open") -> 10 | O7: =SUMPRODUCT(--(COUNTIFS(Quests!$B$2:$B$3000,A7,Quests!$I$2:$I$3000,"Open",Quests!$E$2:$E$3000,{"Leader";"Planner";"Expert";"Maker";"Checker";"Storyteller";"Patron";"User"})>0)) -> 8 | P7: =SUMIF(Budget!$A$2:$A$3000,A7,Budget!$C$2:$C$3000) -> 30000 | Q7: Bill Turner | R7: Retired civil engineer, Ohio | S7: Dayton, USA | T7: New | U7: Lead service lines carry water from the street main into older homes. Lead can leach into tap water, and there is no known safe blood lead level for children. The US EPA estimates about 9 million lead service lines are still in use nationwide. Like other cities, Dayton had to publish an inventory in 2024, but cities across the US list many lines as 'status unknown', and a line nobody has confirmed cannot be put on a replacement schedule. | V7: Households in Dayton's older neighbourhoods, mainly homes built before the 1950s–60s, where lead lines are most likely. Families with young children and renters, who often don't know what pipe they have, benefit first. It also helps the city's water department, which needs confirmed lines to plan and fund replacement. | W7: Confirming each line means someone has to look at the pipe in a basement, and a city crew visit to every home is slow and costly. The pipe is often split in ownership (the city owns one side, the homeowner the other), so nobody owns the whole problem. Residents can identify their own pipe in 5 minutes with a magnet and a coin, but there is no simple, trusted way to collect what they find. | X7: • 500 lead lines replaced, homes with children first • Every address in the public inventory is matched to a block on the map, and 'unknown' lines are counted by block • 1,000 resident photos of 'unknown' lines are checked, with each one called lead, galvanised, copper or plastic • Photo calls match a licensed plumber's check on at least 90% of 40 randomly picked homes • A public block-level map is live and is updated monthly for 12 months • The city publishes a dated plan to replace at least 500 confirmed lead lines, with the confirmed lines first | Y7: • Strictly non-partisan: no candidates, parties or campaigns. Every ask goes to the city through public channels, such as records requests and public comment. • Public records and willing residents only. Photos come only from your own home, or a home whose owner says yes in writing. No door-to-door collection. • Privacy: the map shows status by block. A house appears only if its owner opts in. Photo metadata (GPS, faces) is stripped. • Never cut, unscrew or bend a pipe. A light scratch with a coin and a magnet test is the limit. Wash your hands afterwards. • No health advice beyond public guidance. Point people to the city's and EPA's lead guidance and filter information. | Z7: • Split ownership: the city side and the home side can be different materials, and a basement photo only shows the home side. • Galvanised pipe that was once downstream of lead also counts for replacement under the 2024 rules. Residents can't see the history. • Photos fool people. Painted pipes, wrapped pipes and dark basements make a magnet-and-scratch test the only reliable home check. • Turnout is uneven. Homeowners in better-off streets reply more, but the unknown lines are often in rentals. The map must show where data is missing, not just where lead is. • The city already has a legal deadline. The mission must help it, not compete with it, or the data will be ignored. | AA7: • A neighbourhood association in an older west-side area that hosts sign-up nights (Westwood Porch Network, fictional) • A licensed plumbing co-op that checks 40 random homes to confirm photo accuracy (Gem City Plumbers Co-op, fictional) • A local library branch that lends magnets and hosts help desks (Riverbend Library Friends, fictional) | AB7: • EPA Lead and Copper Rule Revisions (2021): service line inventories due 16 Oct 2024 • EPA Lead and Copper Rule Improvements (2024): replacement within about 10 years • City of Dayton public lead service line inventory • Ohio Public Records Act, ORC 149.43 • Ohio Revised Code 6109.21 (lead line mapping by water systems, from HB 512, 2016) • EPA 'Protect Your Tap' pipe identification guide • Montgomery County Auditor parcel data (year built) • US Census American Community Survey (housing age, renters) • OpenStreetMap and QGIS for the block map | AC7: About 9–12 months. Records take 1–2 months (public records replies can be slow), photos 4–5 months, the map 1–2 months, then 2–3 months to get a dated city plan. The slowest step is getting enough photos from renters and the oldest blocks.
A8: tutor | B8: Learning | C8: Every child can do basic maths | D8: Many children finish primary school without basic maths. Get them there, even where there's no internet. | E8: Final stage | F8: What a finish looks like | G8: 4 | H8: =COUNTIF(Stages!$A$2:$A$1000,A8) -> 4 | I8: 120000 | J8: $ | K8: 180 | L8: =COUNTIF(Squads!$B$2:$B$1000,A8) -> 2 | M8: =COUNTIF(Quests!$B$2:$B$3000,A8) -> 16 | N8: =COUNTIFS(Quests!$B$2:$B$3000,A8,Quests!$I$2:$I$3000,"Open") -> 9 | O8: =SUMPRODUCT(--(COUNTIFS(Quests!$B$2:$B$3000,A8,Quests!$I$2:$I$3000,"Open",Quests!$E$2:$E$3000,{"Leader";"Planner";"Expert";"Maker";"Checker";"Storyteller";"Patron";"User"})>0)) -> 8 | P8: =SUMIF(Budget!$A$2:$A$3000,A8,Budget!$C$2:$C$3000) -> 120000 | Q8: Chioma Okafor | R8: Head teacher, Lagos | S8: 10 countries | T8: Existing · rename from 'Free AI tutor for 1M kids' | U8: Many children finish primary school without being able to do basic maths. UNESCO estimates about 6 in 10 children and teenagers worldwide were not reaching minimum skill in reading and maths. Classes of 40–60 children leave teachers no time for one-to-one help, and most tutoring apps need fast internet and expensive phones. | V8: Children aged 8–11 (roughly Primary 3–5) in low-cost schools in Nigeria, Ghana, Kenya, Tanzania, Uganda, Rwanda, Ethiopia, India, Bangladesh and the Philippines. The pilot reached 500 children in 25 classes. One shared phone serves a small group in class. | W8: Children and schools in these places cannot pay, so companies build for richer markets with good internet. Every country has its own curriculum and language, so one app does not fit all. Few groups run fair tests, so nobody knows which tools really help. | X8: • Works fully offline on a phone costing about $50 (1–2 GB RAM, Android Go) and fits under 150 MB • Covers the national maths curriculum for 3 grade levels in all 10 countries • 500 pilot children use it at least 3 times a week for 4 weeks • In all 10 countries, pilot classes' average score rises at least 10% from their start score and beats the comparison class • Code, content and test items released openly (MIT for code, CC BY 4.0 for content) | Y8: • Child safety first: an adult school staff member is always present, and no player is ever alone with a child. • Written consent from a parent or guardian, and agreement from the head teacher, before any child uses the app or takes a test. • No names, photos or voice of children are stored. Each child gets a code, and the key to the codes stays at the school. • Follow each country's data law (for example the Kenya Data Protection Act 2019, Nigeria Data Protection Act 2023, India DPDP Act 2023). • Report every country's result honestly, including ones that miss the target. | Z8: • Running a helpful tutor on 1–2 GB of RAM with no internet means a tiny model or rule-based hints, not a big chatbot. • 10 curricula and 10 languages: maths words such as 'carry' or 'fraction' differ even between nearby regions. • Fair testing: 4 weeks is short, samples are small (about 50 per country), and teachers may 'teach to the test'. • Phones get shared, lost or run flat. Charging in schools without power is a real limit. • Keeping schools engaged after the pilot ends. | AA8: • A network of low-cost schools in 10 countries (Bright Bench Schools Network, fictional) • A refurbished-phone supplier offering $50 handsets (SecondLife Devices, fictional) • A university education department that reviews the test design (Lakeside University Education Lab, fictional) • A small education fund (Open Slate Fund, fictional) | AB8: • Early Grade Mathematics Assessment (EGMA) open toolkit, used to build the 20-minute test • National curricula: Nigeria NERDC Basic Education Curriculum, Kenya CBC (KICD), India NCERT, Philippines DepEd K-12 MELCs • UNESCO UIS SDG 4.1.1 learning data • Android Go and LiteRT (TensorFlow Lite) for on-device models • Kenya Data Protection Act 2019; Nigeria Data Protection Act 2023; India DPDP Act 2023 • ODK / Kobo-style offline forms for collecting test scores | AC8: About 12 months in total. The slowest step was Stage 3: school permissions and parent consent took 2–3 months in some countries. Stage 4 now waits on the end-of-term Kenya test.
A9: benefits | B9: Society | C9: Get families the benefits they're owed | D9: Help poor families in UP claim the pensions, scholarships and ration they already have a right to. | E9: Racing | F9: Society missions work like science ones | G9: 2 | H9: =COUNTIF(Stages!$A$2:$A$1000,A9) -> 4 | I9: 1500000 | J9: ₹ | K9: 260 | L9: =COUNTIF(Squads!$B$2:$B$1000,A9) -> 3 | M9: =COUNTIF(Quests!$B$2:$B$3000,A9) -> 16 | N9: =COUNTIFS(Quests!$B$2:$B$3000,A9,Quests!$I$2:$I$3000,"Open") -> 9 | O9: =SUMPRODUCT(--(COUNTIFS(Quests!$B$2:$B$3000,A9,Quests!$I$2:$I$3000,"Open",Quests!$E$2:$E$3000,{"Leader";"Planner";"Expert";"Maker";"Checker";"Storyteller";"Patron";"User"})>0)) -> 8 | P9: =SUMIF(Budget!$A$2:$A$3000,A9,Budget!$C$2:$C$3000) -> 1500000 | Q9: Meera Joshi | R9: NGO coordinator, Lucknow | S9: Sitapur & Banda, Uttar Pradesh | T9: New | U9: Families in Uttar Pradesh can claim old-age and widow pensions, free ration under the National Food Security Act, PM-KISAN and student scholarships. Many who qualify never get them. The forms are online, each one needs 2–4 certificates first (income, caste, domicile), and the money only arrives if the bank account is linked to Aadhaar for Direct Benefit Transfer (DBT). A widow aged 40–79 below the poverty line can get a monthly pension, but first she must know it exists, get an income certificate from the tehsil and apply on the state pension portal. | V9: Poor rural families in two UP districts, Sitapur and Banda: widows, elderly people, small farmers and students from SC, ST, OBC and minority families. The helper answers anyone in UP. The on-ground pilot aims at 1,000 families. | W9: Each scheme belongs to a different department with its own portal, rules and documents, so nobody owns the whole picture for one family. Middlemen charge fees to fill free forms, and families stop trusting help. When payments fail because the Aadhaar seeding or the name spelling doesn't match, nobody tells the family why. | X9: • 50 scheme cards checked against the official government orders, each with the benefit, who qualifies, the documents needed and where to apply • The helper answers correctly in 6 languages: at least 90% right on a 30-question test set per language, with zero answers that ask for an Aadhaar number, OTP or bank PIN • 1,000 families in Sitapur and Banda submit complete applications, each with an official registration number • 750 families show a first payment credited in their bank account (passbook or official portal status) • No family pays the mission or a volunteer anything | Y9: • Never collect, photograph or store Aadhaar numbers, OTPs, bank PINs or document copies. Families keep their own papers (Aadhaar Act 2016 Sec. 29, DPDP Act 2023). • Help is always free. Families pay only the official fee at a Common Service Centre (CSC), against a printed receipt. • Apply only through official portals, CSCs or block offices. Never through an agent who promises to 'get it sanctioned'. • Non-partisan: no party names, symbols or leaders' photos on any material, and never tell families a benefit comes from a party. • Any family story or photo needs that family's spoken consent in their own language, and it can be withdrawn at any time. | Z9: • Documents come before schemes. A pension application stalls for weeks until the tehsil issues an income certificate, and caste certificates can take longer. • DBT failures are invisible. A payment 'sent' on the portal bounces if the account isn't Aadhaar-seeded on the NPCI mapper, is dormant, or the name spelling differs between Aadhaar and the bank. • Rules differ by scheme and change by government order: age bands, income limits and whether a widow can draw both the state and central pension. The 50 cards go stale. • Many applicants can't read well. The helper has to work with voice notes in Awadhi or Bundeli, not just typed Hindi. • Sanction sits with officials (BDO, SDM, District Social Welfare Officer). We can help families apply and follow up, but we can't speed up approval. | AA9: • A Lucknow network of form-help NGOs with field staff in Sitapur and Banda (Awadh Seva Sangh, fictional) • A WhatsApp Business solution provider to host the helper number (BolChal Tech, fictional) • Village-level CSC operators in the pilot blocks who agree to post their fees (Sidhauli Digital Seva Kendra, fictional) • A rural bank branch that runs Aadhaar-seeding camps (Gramin Setu Bank, fictional) | AB9: • myScheme portal (myscheme.gov.in) for scheme rules • UP Social Security Pension portal (sspy-up.gov.in) for old-age, widow and disability pensions • UP Scholarship portal (scholarship.up.gov.in) • e-District UP (edistrict.up.gov.in) for income, caste and domicile certificates • National Food Security Act 2013 and UP Food & Civil Supplies portal (fcs.up.gov.in) for ration card status • PM-KISAN beneficiary status page (pmkisan.gov.in) • NSAP guidelines (Indira Gandhi National Widow and Old Age Pension Schemes) • Bhashini (Govt. of India language tools) for first-draft translation, always reviewed by a native speaker • IGRS Jansunwai portal / CM Helpline 1076 and RTI Act 2005 Sec. 6 for stuck applications | AC9: About 10–12 months in total. The slowest step is Stage 4: after a family applies, verification by the block or tehsil and sanction by the district officer often take 1–3 months, and pensions are paid in quarterly instalments.
A10: candidate | B10: Society | C10: Every Pune voter chooses with facts | D10: Candidates' sworn facts are public but buried in long PDFs. Put them in front of voters in Pune district before they vote. | E10: Countdown | F10: Some missions race a deadline (12 days to voting day) | G10: 2 | H10: =COUNTIF(Stages!$A$2:$A$1000,A10) -> 4 | I10: 500000 | J10: ₹ | K10: 120 | L10: =COUNTIF(Squads!$B$2:$B$1000,A10) -> 2 | M10: =COUNTIF(Quests!$B$2:$B$3000,A10) -> 17 | N10: =COUNTIFS(Quests!$B$2:$B$3000,A10,Quests!$I$2:$I$3000,"Open") -> 11 | O10: =SUMPRODUCT(--(COUNTIFS(Quests!$B$2:$B$3000,A10,Quests!$I$2:$I$3000,"Open",Quests!$E$2:$E$3000,{"Leader";"Planner";"Expert";"Maker";"Checker";"Storyteller";"Patron";"User"})>0)) -> 8 | P10: =SUMIF(Budget!$A$2:$A$3000,A10,Budget!$C$2:$C$3000) -> 500000 | Q10: Arjun Mehta | R10: Journalist, Mumbai | S10: Pune district, 21 Assembly seats | T10: New | U10: Every Assembly candidate must file a sworn affidavit (Form 26) listing criminal cases, assets, debts and education. The Election Commission puts them online, but each one is a 15–40 page scanned PDF in dense legal English or Marathi, and few voters ever open one. This election, Pune district's 21 seats have about 310 candidates and 12 days to go. | V10: Voters in Pune district's 21 Assembly constituencies (more than 80 lakh registered voters), especially first-time voters and people who follow the news in Marathi. | W10: Affidavits are scanned images, not data, so every number has to be read and typed by a person. The window between the final candidate list and polling day is only about two weeks. Media cover the big races and skip most independents. Any slip can bring a defamation notice or a charge of bias, so few groups want the risk. | X10: • 310 profiles on one identical template, in Marathi and English • Every fact carries the affidavit page number it came from • Every profile passes 2 independent checks, with zero open factual disputes at publication • 1,00,000 unique visits to profile pages before the 48-hour silence period begins • Equal-treatment audit passed: same fields, same length limit, same order (ballot order from Form 7A) for every candidate | Y10: • Public records only: Form 26 affidavits and the Returning Officer's list of contesting candidates (Form 7A). No social media, news reports or rumours. • Strictly non-partisan: no party logos or colours, no adjectives, no ranking, no 'best' or 'worst'. A pending case is written as 'case pending, not convicted'. • Never publish addresses, PAN, phone numbers, bank details or family members' names, even when the affidavit shows them. • All sharing stops when the 48-hour silence period begins (RP Act 1951 Sec. 126). No paid promotion at any time. • Anyone working for a party or campaign declares it and does not write or check profiles in that constituency. | Z10: • Scans are poor: mixed Marathi and English, handwriting, stamps across text. OCR gets many numbers wrong, so every figure must be read by a person. • Assets are split across self, spouse, HUF and dependents, in movable and immovable tables. Adding them up without double counting is easy to get wrong. • Criminal cases are listed by section number, under the old IPC or the new BNS (in force since July 2024). Turning a section into plain words without implying guilt takes care. • The list keeps changing: withdrawals, rejected nominations and candidates with the same name all arrive days before polling. • Supporters of every side will call the profiles biased, so the process has to be provably the same for everyone. | AA10: • A Pune law college's legal-aid clinic to review the template and risky wording (Deccan Law Clinic, fictional) • A desk of retired Marathi sub-editors for translation (Shabda Desk, fictional) • Housing society federations and college volunteer units to share links (Kothrud Residents' Forum, fictional) • An election-law adviser on call for legal notices (Adv. S. Patwardhan, fictional) | AB10: • Form 26 affidavits on the ECI affidavit portal (affidavit.eci.gov.in) • Conduct of Election Rules 1961, Rule 4A and Form 26 • Form 7A list of contesting candidates from each Returning Officer, via the Chief Electoral Officer, Maharashtra site • Representation of the People Act 1951: Sec. 30 (timeline), Sec. 125A (false affidavit), Sec. 126 (48-hour silence) • ECI Model Code of Conduct and its social media guidance • IPC 1860 and Bharatiya Nyaya Sanhita 2023 section lists, for the plain-language case glossary • Tesseract OCR with the Marathi (mar) model, for first-pass extraction only | AC10: About 4 weeks from the close of nominations to polling day. That's roughly 4 days to collect, 8 days to write profiles, 4 days for second checks and corrections, and 6 days to share before the silence period. The slowest step is the second independent check, because every number has to be traced back to a page.
A11: pothole | B11: Society | C11: No rider hurt by a Bengaluru pothole | D11: Potholes throw Bengaluru's riders off their bikes every week. Get the worst ones fixed fast, and keep them fixed. | E11: Just started | F11: Lots of quick quests on your way home | G11: 1 | H11: =COUNTIF(Stages!$A$2:$A$1000,A11) -> 5 | I11: 800000 | J11: ₹ | K11: 340 | L11: =COUNTIF(Squads!$B$2:$B$1000,A11) -> 2 | M11: =COUNTIF(Quests!$B$2:$B$3000,A11) -> 17 | N11: =COUNTIFS(Quests!$B$2:$B$3000,A11,Quests!$I$2:$I$3000,"Open") -> 10 | O11: =SUMPRODUCT(--(COUNTIFS(Quests!$B$2:$B$3000,A11,Quests!$I$2:$I$3000,"Open",Quests!$E$2:$E$3000,{"Leader";"Planner";"Expert";"Maker";"Checker";"Storyteller";"Patron";"User"})>0)) -> 8 | P11: =SUMIF(Budget!$A$2:$A$3000,A11,Budget!$C$2:$C$3000) -> 800000 | Q11: Kavya Iyer | R11: Product manager, Bengaluru | S11: Bengaluru, India | T11: New | U11: Bengaluru has roughly 13,000–14,000 km of city-run roads, and potholes come back after every monsoon. People complain on the city's Sahaaya app or the 1533 helpline, but many complaints are closed without a repair, and nobody publishes ward-by-ward fix rates. Two-wheeler riders take most of the risk. | V11: Bengaluru's 1.3 crore or so residents, above all two-wheeler riders, delivery workers, cyclists and pedestrians. The pilot covers 20 wards in the east and south of the city, then expands. | W11: Roads belong to different owners: the city corporation, BDA, NHAI, metro works, and water or power utilities that dig trenches. Each can point at another. Contractors are paid per job, and defect-liability clauses that should force free re-repair are rarely enforced. The complaint system measures closure, not repair, and city governance and ward maps are being reorganised, so it's often unclear which officer is responsible. | X11: • Pothole crashes on mapped roads fall by half • 5,000 unique potholes pinned, each with a photo, GPS, time, size and road owner • At least 95% of verified pins filed through an official channel, each with a complaint ID • 80% of filed potholes show a verified repair (after-photo) within 90 days • A public ward scoreboard showing median days to fix, updated weekly • Zero road-safety incidents among players | Y11: • Never photograph from a moving vehicle or while standing in traffic. Pull over first or skip it. • No faces or number plates in photos. Blur them before uploading. • One pin per pothole. File only through official channels, from your own account. No fake, duplicate or bulk bot complaints. • Publish ward and office numbers, never personal attacks on named engineers or workers. • Non-partisan: no party or candidate branding, and the data is shared equally with anyone who asks. | Z11: • Duplicates: phone GPS drifts 5–20 m between buildings, so two riders pin the same pothole as two. • Road ownership: a pothole inside a metro work zone or over a water-board trench is not the corporation's job, and the complaint bounces. • 'Closed' is not 'fixed'. Proving a repair needs a second visit and an after-photo. • Monsoon patches with cold mix often fail within weeks, so a 'fixed' pothole can reopen before day 90. • Ward boundaries and officer lists are changing under the new city corporations, so pins must be re-mapped when new boundaries are published. | AA11: • Delivery-rider community groups who pin on routes they already ride (Rider Saathi Collective, fictional) • Resident welfare associations in pilot wards (South-East RWA Forum, fictional) • A civic-tech volunteer group to host the map and scoreboard (OpenRaasta Labs, fictional) • A retired road engineer to judge repair quality (Kere Roads Advisory, fictional) | AB11: • Sahaaya grievance app and the 1533 helpline (the city's official complaint channels) • Greater Bengaluru Governance Act 2024 (city corporations and ward committees) • BBMP 198-ward boundary files on open civic data portals, plus newly notified ward maps when published • OpenStreetMap road network for snapping pins to roads • IRC:82 Code of Practice for Maintenance of Bituminous Roads (Indian Roads Congress) • RTI Act 2005 Sec. 6 for road work orders and defect-liability periods • Karnataka Public Procurement portal (KPPP) for road repair tenders | AC11: About 7–9 months. That's 6–8 weeks to map, 3–4 weeks to file, then a 90-day tracking window for the last batch. The slowest step is waiting for repairs: crews prioritise main roads and hold back work in heavy rain.
A12: rti | B12: Society | C12: Every rupee reaches Bihar's schools | D12: Money for toilets, books and teachers is sent, but often never arrives. Follow it to 100 schools and get the gaps fixed. | E12: Stuck | F12: Real-world blockers need people, not just agents | G12: 3 | H12: =COUNTIF(Stages!$A$2:$A$1000,A12) -> 6 | I12: 600000 | J12: ₹ | K12: 55 | L12: =COUNTIF(Squads!$B$2:$B$1000,A12) -> 2 | M12: =COUNTIF(Quests!$B$2:$B$3000,A12) -> 17 | N12: =COUNTIFS(Quests!$B$2:$B$3000,A12,Quests!$I$2:$I$3000,"Open") -> 10 | O12: =SUMPRODUCT(--(COUNTIFS(Quests!$B$2:$B$3000,A12,Quests!$I$2:$I$3000,"Open",Quests!$E$2:$E$3000,{"Leader";"Planner";"Expert";"Maker";"Checker";"Storyteller";"Patron";"User"})>0)) -> 8 | P12: =SUMIF(Budget!$A$2:$A$3000,A12,Budget!$C$2:$C$3000) -> 600000 | Q12: Rajesh Kumar | R12: Retired teacher, Patna | S12: Bihar, India | T12: New | U12: Every year each Bihar government school gets grants under Samagra Shiksha, for example a composite school grant of ₹10,000 to ₹1,00,000 depending on how many children are enrolled. Parents almost never see how much came in or what it bought. Toilets show up as 'functional' on UDISE+ but are locked or broken, and library books are bought on paper but not on the shelf. | V12: Parents, School Management Committee (Vidyalaya Shiksha Samiti) members and teachers at 100 government primary and middle schools in Patna, Gaya, Muzaffarpur and Purnia districts. Roughly 25,000 to 35,000 children study there. | W12: The money flows through block and district offices, so no one at the school level sees the whole picture. RTI replies often come late, appeals take many months, and one parent asking alone is easy to ignore. Comparing paper with reality takes 100 site visits, and nobody is paid to do them. | X12: • 50 schools get what was missing • 100 RTI replies received (or a Commission order for each missing one) • 100 school visits done with a 12-item checklist and timestamped photos • 100 one-page report cards published in Hindi, each with the school's right of reply attached • Every gap above ₹5,000 or one missing facility backed by two documents (RTI reply + visit photo) • Report cards presented at 20 or more School Management Committee meetings | Y12: • Strictly non-partisan. No party names, no politicians, no blame language. Report what the papers say and what we saw. • Public records only. No children's faces or names in photos. No staff personal data beyond name and post as given in the RTI reply. • On-ground visits only in school hours, in pairs, after the head teacher says yes. No entry if refused. Note the refusal and leave. • Each school gets 15 days to answer before its report card is published, and the answer is printed beside our findings. • No bribes and no 'speed money', ever. If someone asks for one, log it and leave. | Z12: • PIOs transfer applications under Sec. 6(3) or reply 'information not held', and every transfer restarts a 5-day clock and a new paper trail. • Replies arrive as scanned cashbooks and PFMS printouts in mixed Hindi and English. Turning them into comparable numbers is slow, careful work. • Second appeals at the State Information Commission can wait months for a hearing, and the hearing is in Patna, far from rural applicants. • Grant heads differ by year and by school category, so 'missing money' is often a coding difference rather than theft. You have to know the Samagra Shiksha norms to tell which. • Head teachers may feel accused. Without their trust, visits get refused. | AA12: • A retired-teachers' association that lends volunteers for appeals and visits (Purana Shikshak Manch, fictional) • A law-college RTI clinic that checks appeal drafts (Patliputra Law Clinic, fictional) • A parents' network active in 20 School Management Committees (Abhibhavak Sangh Bihar, fictional) | AB12: • RTI Act 2005: Sec. 6 (application), Sec. 7(1) (30-day reply), Sec. 7(5) (no fee for BPL), Sec. 19(1) and 19(3) (first and second appeal), Sec. 20 (penalty) • Bihar Right to Information Rules 2006 (₹10 fee by cash, demand draft or postal order) • UDISE+ school-level data (enrolment, toilets, library, teachers) and school report cards • Samagra Shiksha Framework for Implementation (composite school grant norms) and Bihar PAB minutes • PFMS fund-transfer records as supplied in RTI replies • India Post registered post tracking (proof of filing) | AC12: About 12 to 15 months in total. The slowest step is stage 3: 30 days for a reply, 30 to 45 days for a first appeal, then often 4 to 9 months before a second appeal is heard at the Commission.
A13: flood | B13: Society | C13: No Lagos family caught by a flood | D13: Floods hit Lagos streets with no warning. Give families two hours to move people and things to safety. | E13: Plan in review | F13: The mission creator OKs each new plan | G13: 1 | H13: =COUNTIF(Stages!$A$2:$A$1000,A13) -> 4 | I13: 25000 | J13: $ | K13: 12 | L13: =COUNTIF(Squads!$B$2:$B$1000,A13) -> 2 | M13: =COUNTIF(Quests!$B$2:$B$3000,A13) -> 16 | N13: =COUNTIFS(Quests!$B$2:$B$3000,A13,Quests!$I$2:$I$3000,"Open") -> 9 | O13: =SUMPRODUCT(--(COUNTIFS(Quests!$B$2:$B$3000,A13,Quests!$I$2:$I$3000,"Open",Quests!$E$2:$E$3000,{"Leader";"Planner";"Expert";"Maker";"Checker";"Storyteller";"Patron";"User"})>0)) -> 8 | P13: =SUMIF(Budget!$A$2:$A$3000,A13,Budget!$C$2:$C$3000) -> 25000 | Q13: Femi Adeyemi | R13: Telecom engineer, Lagos | S13: Lagos, Nigeria | T13: New | U13: Every rainy season (April to October) parts of Lagos flood. Families in Ogun River communities like Isheri North often learn the water is coming only when it reaches the door. National outlooks name Lagos as high-risk every year, but they work at the scale of a whole LGA and a whole season, not a street on a given night. Nigeria's 2012 floods killed about 360 people nationally, and the 2022 floods killed more than 600. | V13: About 10,000 households (roughly 40,000 people) along the lower Ogun River (Isheri North, Ikosi-Isheri) and one flood-prone Lagos canal, starting in Kosofe and Ikosi-Isheri areas. | W13: Gauges get installed by projects and then stop working when the grant ends: batteries die, SIMs expire, sensors get stolen. Alerts need a trusted local sender and the right language, and nobody owns the cost of SMS after launch. Upstream dam-release information is not shared in a form residents can act on. | X13: • 20 sensors (14 water-level, 6 rain) online with at least 90% uptime for a full rainy month • 10,000 phones opted in by SMS keyword, with at least 60% choosing Yoruba or Pidgin • In 4 of 5 real flood events at the Ogun River sites, alerts arrived 2 or more hours before water reached the marked street level • False alarms make up fewer than 1 in 4 alerts over the season • A signed handover with 12 months of SIM, SMS and repair costs funded, and 2 trained local technicians | Y13: • Never install or check sensors when water is rising or after dark. Two people at every river visit. • Opt-in only. Phone numbers are stored encrypted, used only for flood alerts, and deleted on 'STOP'. • Alerts say what the water is doing and what to do. They never blame anyone and never contradict official LASEMA or NEMA evacuation orders. • Every sensor site needs written OK from the landowner or community, plus the CDA chair. • Open hardware and open data. Water-level readings are published so others can reuse them. | Z13: • Setting thresholds. Too low and people ignore the alerts. Too high and the warning arrives too late. Every site needs its own threshold, tuned against real events. • Keeping sensors alive through a rainy season: solar panels shaded by roofs, enclosures flooding, cables cut, theft. • Bulk SMS in Nigeria needs a registered sender ID and has to deal with Do-Not-Disturb filtering. Alerts that arrive late or not at all are worse than no alerts. • Ogun River levels depend on Oyan Dam releases upstream. Without release information, the gauge alone gives less warning. • Getting a local body to take over the running costs after the mission ends. | AA13: • A residents' Community Development Association that hosts sensors and owns the handover (Isheri Riverside CDA, fictional) • A maker space that builds and repairs gauges (Yaba Hardware Lab, fictional) • A licensed bulk-SMS aggregator with a registered short code (TextWave Nigeria, fictional) • A university hydrology group that checks thresholds (Lagoon Hydrology Group, fictional) | AB13: • NIHSA Annual Flood Outlook (Nigeria Hydrological Services Agency), yearly • NiMet Seasonal Climate Prediction • GloFAS (Copernicus Global Flood Awareness System) river forecasts • OpenStreetMap waterways and buildings; Humanitarian OpenStreetMap Tasking Manager • Common Alerting Protocol (CAP 1.2, OASIS) for alert messages • NCC rules on bulk SMS sender IDs and Do-Not-Disturb (2442) • Open hardware: ESP32 board, JSN-SR04T ultrasonic or radar level sensor, tipping-bucket rain gauge, 2G/4G modem, solar panel | AC13: About 14 to 18 months: build and install before the April rains, run a full rainy season (April to October), then hand over. The slowest step is stage 3, because you have to wait for real floods to test against.
... A18: air | B18: Planet | C18: Fresh air in every classroom | D18: Stale air makes kids sleepy and sick. Tell teachers when to open a window, with a sensor schools can afford. | E18: Stopped | F18: Failure is safe: unspent money goes back | G18: 2 | H18: =COUNTIF(Stages!$A$2:$A$1000,A18) -> 2 | I18: 18000 | J18: $ | K18: 61 | L18: =COUNTIF(Squads!$B$2:$B$1000,A18) -> 1 | M18: =COUNTIF(Quests!$B$2:$B$3000,A18) -> 5 | N18: =COUNTIFS(Quests!$B$2:$B$3000,A18,Quests!$I$2:$I$3000,"Open") -> 0 | O18: =SUMPRODUCT(--(COUNTIFS(Quests!$B$2:$B$3000,A18,Quests!$I$2:$I$3000,"Open",Quests!$E$2:$E$3000,{"Leader";"Planner";"Expert";"Maker";"Checker";"Storyteller";"Patron";"User"})>0)) -> 0 | P18: =SUMIF(Budget!$A$2:$A$3000,A18,Budget!$C$2:$C$3000) -> 18000 | Q18: Sofia Rossi | R18: Retired accountant, Milan | S18: Global | T18: New · finished list | U18: Crowded classrooms with closed windows build up stale air quickly. CO2 is a simple sign of that: outdoor air is about 420 ppm, and classrooms often climb past 1,000–1,500 ppm during lessons. Teachers can't feel it happening. Good CO2 meters cost $100 or more, which is too much for most schools to buy one per room. | V18: Teachers and pupils in ordinary state schools, starting with 10 pilot classrooms. The plan was to reach about 200 classrooms if the price held. | W18: Accurate CO2 sensing needs an infrared (NDIR) sensor, and that part alone costs more than the whole $20 target in small batches. Cheap chips that claim to read CO2 actually estimate it from other gases and can be very wrong. Schools rarely have a budget line for air monitoring. | X18: • Sensor reads within ±100 ppm (plus a few %) of a reference meter from 400 to 2,000 ppm • Full parts and build cost of $20 or less per unit at a 50-unit batch • A teacher can read it at a glance (green/amber/red) without an app • 50 units running in 10 classrooms for 4 weeks | Y18: • No personal data: the sensor records CO2, temperature and time only, with no microphones and no cameras. • Open hardware and firmware under an open licence (CERN-OHL and MIT). • Safe power: USB power only and certified chargers. No mains wiring is done by players. • Classroom trials only with the school's written OK. • If the goal can't be met, stop and refund rather than quietly change it. | Z18: • Cost versus accuracy: cheap 'eCO2' chips are inaccurate, and accurate NDIR sensors are expensive. • Calibration: NDIR sensors drift and need a fresh-air baseline. Classrooms are rarely empty long enough for automatic calibration. • Small batches cost more per unit: cases, boards and shipping are priced for volumes of 1,000 or more. • Teachers need a simple signal, not a graph. | AA18: • A school in Milan that hosted the pilot (Scuola Primaria Navigli, fictional) • A maker space that lent a reference CO2 meter and a soldering bench (Officina Lambro, fictional) | AB18: • NDIR CO2 sensor modules (open datasheets) • ESP32 microcontroller and ESPHome / Arduino firmware • CERN Open Hardware Licence v2 • UK Department for Education BB101 guidance on classroom ventilation (CO2 levels) • ASHRAE Standard 62.1 (ventilation background) • KiCad for the circuit board | AC18: 4 months, then stopped. A full run would have taken about 8 months. The slowest step was getting real quotes for 50-unit batches. That should have been done first.

Sheet Stages
A1: Mission ID | B1: # | C1: Stage | D1: Goal (countable) | E1: Target | F1: Unit | G1: Progress | H1: % done | I1: Status | J1: In plain words | K1: Why this stage | L1: Workstreams | M1: How the roles fit together | N1: Done when | O1: Who approves | P1: Depends on | Q1: Main risk | R1: Budget share | S1: Duration | T1: Quests | U1: Your notes
A2: glio | B2: 1 | C2: Recon | D2: Map every open brain tumour dataset | E2: 40 | F2: datasets | G2: 40 | H2: =IFERROR(G2/E2,0) -> 1 | I2: Done | J2: Find all the free data we can learn from. | K2: Every later step learns from this data, so we need to know what exists and what we may legally use. | L2: • Find datasets • Record licence and access rules • Note data quality and size | M2: The Planner sets the fields, Experts find datasets, the Maker builds the catalogue, and Checkers confirm each licence before it counts. | N2: 40 datasets in the catalogue, each with a link, licence, size and an access note, checked by 2 Checkers. | O2: Mission creator + 2 Checkers | P2: Nothing | Q2: Restricted-access data mistaken for open data. | R2: 0.05 | S2: 4–6 weeks | T2: =COUNTIFS(Quests!$B$2:$B$3000,A2,Quests!$L$2:$L$3000,B2) -> 1
A3: glio | B3: 2 | C3: Hypothesis | D3: Rank the top 50 drug targets | E3: 50 | F3: targets | G3: 50 | H3: =IFERROR(G3/E3,0) -> 1 | I3: Done | J3: Pick the weak spots in the tumour to aim at. | K3: Aiming the search beats searching everything. | L3: • Pull evidence from public platforms • Score each target on agreed criteria • Review the ranking | M3: The Leader sets the rule, the Maker pipes in public evidence, Experts score it, and Checkers re-check citations before the ranking is published. | N3: 50 targets ranked, each with cited public evidence; 2 Checkers agree on the top 20. | O3: Mission creator + 2 expert Checkers | P3: Stage 1 catalogue | Q3: Ranking driven by one dataset. | R3: 0.1 | S3: 6–8 weeks | T3: =COUNTIFS(Quests!$B$2:$B$3000,A3,Quests!$L$2:$L$3000,B3) -> 1
A4: glio | B4: 3 | C4: Simulate | D4: Shortlist 10 drug candidates | E4: 10 | F4: candidates | G4: 4 | H4: =IFERROR(G4/E4,0) -> 0.4 | I4: Now | J4: Find 10 drugs that might kill this tumour, and prove each one on real data. | K4: Computer screens are cheap; lab time is not, so we narrow down first. | L4: • Large compute screen (Fold Gang) • Approved-drug review (Wet Hands) • Generated designs (Swarm 404) • Independent re-runs and reviews | M4: Patrons fund the compute, Makers run batches, Checkers re-run samples, and Experts add published evidence. The Leader applies the shortlist rule, and the Planner lines up lab quotes so Stage 4 can start. | N4: 10 candidates, each with re-run results matching within the agreed tolerance and an evidence summary signed by an Expert and 2 Checkers. | O4: Mission creator + 2 Checkers + 1 outside Expert | P4: Stage 2 ranked targets | Q4: False positives; unchecked generated designs. | R4: 0.3 | S4: 3–4 months | T4: =COUNTIFS(Quests!$B$2:$B$3000,A4,Quests!$L$2:$L$3000,B4) -> 12
A5: glio | B5: 4 | C5: Wet lab | D5: Test the top 10 in a partner lab | E5: 10 | F5: drugs tested | G5: 0 | H5: =IFERROR(G5/E5,0) -> 0 | I5: Locked | J5: Test the 10 on real tumour cells. | K5: Only real lab results show whether the computer was right. | L5: • Lab contract and budget • Shipping and paperwork • Independent result review | M5: Patrons fund the fees, the Planner books and ships, partner-lab staff test, Checkers review the report, and Storytellers publish all results. | N5: Partner lab report received for all 10, with raw data published and reviewed by 2 Checkers. | O5: Mission creator + 2 Checkers + partner lab sign-off | P5: Stage 3 shortlist and signed lab contract | Q5: Lab slot delays; budget overrun. | R5: 0.4 | S5: 6–9 months | T5: =COUNTIFS(Quests!$B$2:$B$3000,A5,Quests!$L$2:$L$3000,B5) -> 1
A6: glio | B6: 5 | C6: Trial | D6: Request a pre-IND meeting with a trial sponsor | E6: 1 | F6: filing | G6: 0 | H6: =IFERROR(G6/E6,0) -> 0 | I6: Locked | J6: Ask to test the best one in a few patients. | K6: Regulators decide whether a trial can start; we bring the open evidence to a sponsor who can run it. | L6: • Find a sponsor • Assemble the data package • Plain-language patient summary | M6: The Leader secures a sponsor, the Planner and an Expert consultant assemble the package, and Storytellers explain it to patients. | N6: A sponsor submits the meeting request with our package. | O6: Mission creator + sponsor + regulatory consultant | P6: Stage 4 results | Q6: No sponsor willing. | R6: 0.15 | S6: 6–12 months | T6: =COUNTIFS(Quests!$B$2:$B$3000,A6,Quests!$L$2:$L$3000,B6) -> 1
A7: aid | B7: 1 | C7: Know what kills | D7: Choose the 20 emergencies where a bystander saves the most lives | E7: 20 | F7: emergencies | G7: 14 | H7: =IFERROR(G7/E7,0) -> 0.7 | I7: Now | J7: Find the emergencies where the first few minutes decide who lives | K7: Everything else multiplies by this list, so it must be right before we translate 1,000 times. | L7: • Choose and justify the 20 topics • Write plain English master text • Pilot the translate-and-check loop on 2 guides • Recruit language leads | M7: Expert nurses propose and write masters, a User says what confuses them, then the Leader freezes the 20. The Planner turns the pilot timing from Checkers into a language plan while Storytellers recruit and Patrons fund the pay. | N7: 20 master guides each under 250 words, each approved by 2 licensed nurses, and the pilot shows a check takes under 30 minutes. | O7: Mission creator + 2 nurse Checkers | P7: Agreed guideline sources (IFRC 2020) | Q7: Endless debate over the last 6 topics; masters too long to translate well. | R7: 0.15 | S7: 4–6 weeks | T7: =COUNTIFS(Quests!$B$2:$B$3000,A7,Quests!$L$2:$L$3000,B7) -> 12
A8: aid | B8: 2 | C8: Translate | D8: Translate them into 50 languages | E8: 50 | F8: languages | G8: 0 | H8: =IFERROR(G8/E8,0) -> 0 | I8: Locked | J8: Agents draft, people who speak the language fix. | K8: Only once masters are frozen can we draft without redoing work. | L8: • Build a glossary per language (30 key terms) • Agent drafts for all 20 guides • Native-speaker fix pass • Font and script checks | M8: Makers run agent drafts, Experts fix them using a Checker-approved glossary, and the Planner moves speakers to languages that lag. | N8: 50 languages each have 20 fixed drafts and an approved glossary in Weblate. | O8: Language lead + 1 Checker per language | P8: Frozen master text and the Stage 1 pilot workflow | Q8: No speakers found for the last 10 languages. | R8: 0.4 | S8: 3–4 months | T8: =COUNTIFS(Quests!$B$2:$B$3000,A8,Quests!$L$2:$L$3000,B8) -> 2
A9: aid | B9: 3 | C9: Check | D9: A native speaker checks every guide | E9: 1000 | F9: guides checked | G9: 0 | H9: =IFERROR(G9/E9,0) -> 0 | I9: Locked | J9: Every guide is checked by someone who grew up speaking it. | K9: A second, independent speaker catches what the fixer missed before anything reaches the public. | L9: • Independent native-speaker check • Back-translation of 1 in 10 to English • Nurse review of flagged items | M9: Checkers mark every pair, back-translations flag risky lines for nurse Experts, and the Leader orders re-checks where a language fails. | N9: 1,000 pairs marked checked; back-translated sample has zero safety-changing errors. | O9: 2 Checkers per language + 1 nurse for flagged items | P9: Stage 2 drafts and glossaries | Q9: Checker is the same person who translated; quality drifts. | R9: 0.3 | S9: 2–3 months | T9: =COUNTIFS(Quests!$B$2:$B$3000,A9,Quests!$L$2:$L$3000,B9) -> 2
A10: aid | B10: 4 | C10: Ready | D10: 10,000 people have the guides on their phone or wall | E10: 10000 | F10: people | G10: 0 | H10: =IFERROR(G10/E10,0) -> 0 | I10: Locked | J10: Put the help where people will be when it happens | K10: Content only helps once it is on phones and walls. | L10: • Offline app • Print-ready cards • Local launch posts per language | M10: Makers package checked text, Checkers test on real phones, the Leader signs off, and Storytellers and Users spread it. | N10: App works offline on a 2 GB Android phone in all 50 languages; card PDFs print correctly on A5. | O10: Mission creator + 3 Checkers testing on real phones | P10: All 1,000 pairs checked | Q10: App too big for cheap phones; nobody hears about it. | R10: 0.15 | S10: 4–6 weeks | T10: =COUNTIFS(Quests!$B$2:$B$3000,A10,Quests!$L$2:$L$3000,B10) -> 2
A11: llm | B11: 1 | C11: Data | D11: Gather 20 billion words of open text in 22 languages | E11: 22 | F11: languages | G11: 9 | H11: =IFERROR(G11/E11,0) -> 0.40909091 | I11: Now | J11: Collect free, legal text in every Indian language. | K11: No model can be better than its text, and the tests must be frozen before training so they cannot leak in. | L11: • Find and licence-check sources for all 22 languages • Clean, fix fonts, deduplicate and language-ID the text • Build and test the shared tokenizer • Write and freeze native test sets | M11: Expert finds and cleans licensed text → Maker dedups it and builds the tokenizer → Checker samples and audits licences → Leader freezes the corpus. Storyteller and Patron keep the rare-language Experts coming and paid. | N11: 22 of 22 languages have at least 5 million clean words each, with 20 billion or more words in total. Every source has a licence-log line. 2 Checkers sample 200 lines per language and find 5% junk or less. Test sets are hashed and frozen. | O11: Mission creator + 2 Checkers per language (native speakers) | P11: Squads formed; licence policy agreed | Q11: The smallest 6–8 languages stall below the floor because no licensed text exists and nobody can be found to write or clean it. | R11: 0.3 | S11: 12–16 weeks | T11: =COUNTIFS(Quests!$B$2:$B$3000,A11,Quests!$L$2:$L$3000,B11) -> 12
A12: llm | B12: 2 | C12: Train | D12: Train a 1–2 billion-parameter model on 64 GPUs | E12: 1 | F12: trained model | G12: 0 | H12: =IFERROR(G12/E12,0) -> 0 | I12: Locked | J12: Teach the model from that text. | K12: Training only makes sense once the data and tokenizer are fixed. Every change after the run starts wastes GPU money. | L12: • Small test runs (100M–400M parameters) to set the language mix • Main 1–2B run on 64 GPUs with checkpoints every 2 hours • Instruction tuning on native-written examples | M12: Leader picks the size from the test runs → Patron funds the booking → Maker launches the crash-safe run → Expert-written instructions tune it → Checker confirms it trained cleanly. | N12: A 1–2B model finishes its planned token budget without lost progress. Loss curves and checkpoints are published. A quick check shows held-out loss falling in all 22 languages. | O12: Squad Leader + 2 Checkers (ML) who re-run 3 evaluation scripts on the final checkpoint | P12: Stage 1 corpus and tokenizer frozen; GPU booking paid | Q12: GPU money runs out mid-run, or a bad data mix makes the model ignore the small languages. | R12: 0.45 | S12: 5–8 weeks | T12: =COUNTIFS(Quests!$B$2:$B$3000,A12,Quests!$L$2:$L$3000,B12) -> 2
A13: llm | B13: 3 | C13: Test | D13: Match or beat same-size open models in 15 of 22 languages | E13: 15 | F13: languages | G13: 0 | H13: =IFERROR(G13/E13,0) -> 0 | I13: Locked | J13: Publish all 22 scores, wins and losses. | K13: A model is only useful if we can show, language by language, where it helps and where it does not. | L13: • Run open benchmarks (IN22, FLORES-200, IndicXTREME) • Run the frozen native test sets • Human grading of open-ended answers by native speakers • Compare against open models of the same size | M13: Maker runs the benchmarks → Experts grade the open answers → Checker re-runs a sample → Leader signs the table → Storyteller publishes wins and losses. | N13: Scores for all 22 languages are published in one table with confidence ranges. The model matches or beats the same-size baselines in at least 15 languages. 2 Checkers re-run 10% of the scoring and get the same numbers within 1 point. | O13: Mission creator + 2 Checkers + 1 Expert per language for human grading | P13: Stage 2 final checkpoint | Q13: Benchmarks for rare languages are too small to separate models, so 'wins' are noise. | R13: 0.17 | S13: 6–8 weeks | T13: =COUNTIFS(Quests!$B$2:$B$3000,A13,Quests!$L$2:$L$3000,B13) -> 1
... A68: air | B68: 2 | C68: Pilot | D68: Build 50 sensors at $20 or less each for 10 classrooms | E68: 50 | F68: sensors | G68: 50 | H68: =IFERROR(G68/E68,0) -> 1 | I68: Done | J68: Make enough for 10 classrooms at the target price. Stopped here. | K68: Prove the price at a real batch size before going to 200 classrooms. | L68: • Real quotes for 50 units • Simplified display • Classroom trial with 4 units | M68: Planner got quotes → Checker audited them at $90 → teachers (Users) liked the 4 trial units → Leader and backers voted to stop → Storyteller explained the stop. | N68: 50 units built at $20 or less each, all passing accuracy checks | O68: Mission creator + 2 Checkers | P68: Stage 1 passed | Q68: Batch cost is far above target, which is what happened. | R68: 0.6 | S68: 10 weeks (stopped) | T68: =COUNTIFS(Quests!$B$2:$B$3000,A68,Quests!$L$2:$L$3000,B68) -> 3
A69: glio | B69: 6 | C69: Patients | D69: First 20 patients treated in a trial | E69: 20 | F69: patients | G69: 0 | H69: =IFERROR(G69/E69,0) -> 0 | I69: Locked | J69: The treatment reaches real people | K69: A filing is a promise; patients treated is the win. | N69: 20 patients dosed under an approved trial protocol, reported publicly | O69: Trial sponsor + mission creator | P69: Stage 5 passed | T69: =COUNTIFS(Quests!$B$2:$B$3000,A69,Quests!$L$2:$L$3000,B69) -> 0
A70: aid | B70: 5 | C70: Act | D70: Bystanders step in during 100 real emergencies | E70: 100 | F70: emergencies | G70: 0 | H70: =IFERROR(G70/E70,0) -> 0 | I70: Locked | J70: People act when it counts | K70: Guides only matter if someone uses them in the moment. | N70: 100 reports of a bystander using a guide, each confirmed by a nurse Checker | O70: Mission creator + 2 nurse Checkers | P70: Stage 4 passed | T70: =COUNTIFS(Quests!$B$2:$B$3000,A70,Quests!$L$2:$L$3000,B70) -> 0
A71: llm | B71: 5 | C71: Use | D71: 10,000 people use it every week in their own language | E71: 10000 | F71: people | G71: 0 | H71: =IFERROR(G71/E71,0) -> 0 | I71: Locked | J71: People use it in their language, every week | K71: A model nobody uses fixes nothing. | N71: 10,000 weekly users for 4 weeks, counted without personal data | O71: Mission creator + 2 Checkers | P71: Stage 4 passed | T71: =COUNTIFS(Quests!$B$2:$B$3000,A71,Quests!$L$2:$L$3000,B71) -> 0
A72: lead | B72: 5 | C72: Replaced | D72: 500 lead lines replaced | E72: 500 | F72: pipes | G72: 0 | H72: =IFERROR(G72/E72,0) -> 0 | I72: Locked | J72: The lead pipes are gone | K72: A plan is a promise; a replaced pipe is safe water. | N72: 500 replacements confirmed in the city's public records | O72: Mission creator + 2 Checkers | P72: Stage 4 passed | T72: =COUNTIFS(Quests!$B$2:$B$3000,A72,Quests!$L$2:$L$3000,B72) -> 0
A73: pothole | B73: 5 | C73: Safer | D73: Pothole crashes on mapped roads fall by half | E73: 50 | F73: % fewer | G73: 0 | H73: =IFERROR(G73/E73,0) -> 0 | I73: Locked | J73: Fewer riders get hurt | K73: Fixed potholes only matter if fewer people fall. | N73: Crash reports on mapped roads down 50% against the same months last year | O73: Mission creator + 2 Checkers | P73: Stage 4 passed | T73: =COUNTIFS(Quests!$B$2:$B$3000,A73,Quests!$L$2:$L$3000,B73) -> 0
A74: rti | B74: 6 | C74: Fixed | D74: 50 schools get what was missing | E74: 50 | F74: schools | G74: 0 | H74: =IFERROR(G74/E74,0) -> 0 | I74: Locked | J74: The money turns into toilets, books and teachers | K74: A report card shows the gap; the win is closing it. | N74: 50 schools show the missing items in place, with dated photos | O74: Mission creator + 2 Checkers | P74: Stage 5 passed | T74: =COUNTIFS(Quests!$B$2:$B$3000,A74,Quests!$L$2:$L$3000,B74) -> 0
A75: renter | B75: 5 | C75: Fixed | D75: 500 repairs made or deposits returned | E75: 500 | F75: renters | G75: 0 | H75: =IFERROR(G75/E75,0) -> 0 | I75: Locked | J75: Renters get the repair or the money back | K75: Sending a letter is a step; the repair is the win. | N75: 500 renters confirm the repair or refund, with a photo or receipt | O75: Mission creator + 2 Checkers | P75: Stage 4 passed | T75: =COUNTIFS(Quests!$B$2:$B$3000,A75,Quests!$L$2:$L$3000,B75) -> 0

Sheet Role map
A1: Mission ID | B1: # | C1: Stage | D1: Status | E1: Leader | F1: Planner | G1: Expert | H1: Maker | I1: Checker | J1: Storyteller | K1: Patron | L1: User
A2: glio | B2: 1 | C2: Recon | D2: Done | F2: Sets catalogue fields | G2: Finds and judges datasets | H2: Builds the searchable catalogue | I2: Verifies links and licences | L2: Patients flag datasets they've heard of
A3: glio | B3: 2 | C3: Hypothesis | D3: Done | E3: Agrees the scoring rule | G3: Scores evidence | H3: Builds the scoring pipeline | I3: Re-checks citations | J3: Explains the ranking plainly
A4: glio | B4: 3 | C4: Simulate | D4: Now | E4: Sets the shortlist rule | F4: Gets lab quotes ahead of Stage 4 | G4: Reviews published evidence | H4: Runs compute batches and models | I4: Re-runs samples and reviews reports | J4: Recruits Checkers and posts progress | K4: Funds compute and squads | L4: Reads updates and asks questions
A5: glio | B5: 4 | C5: Wet lab | D5: Locked | E5: Signs the contract | F5: Books lab time and paperwork | I5: Reviews the lab report | J5: Publishes results, including failures | K5: Funds lab fees
A6: glio | B6: 5 | C6: Trial | D6: Locked | E6: Finds the sponsor | F6: Manages the package | G6: Regulatory consultant advises | J6: Writes the patient summary | K6: Funds consulting
A7: aid | B7: 1 | C7: Pick | D7: Now | E7: Freezes the final list of 20 | F7: Plans language waves and the check workflow | G7: Nurses propose topics and write plain master text | H7: Draws wordless pictures that set the style | I7: Pilots the check loop and times it | J7: Recruits speakers for missing languages | K7: Funds translator pay for small languages | L7: Reads a draft and says what is unclear
A8: aid | B8: 2 | C8: Translate | D8: Locked | F8: Tracks 50 languages against the wave plan | G8: Native speakers build glossaries and fix drafts | H8: Sets up Weblate and agent drafting | I8: Approves each glossary | J8: Keeps recruiting for gaps | K8: Pays per finished language | L8: Tries a draft on a phone
A9: aid | B9: 3 | C9: Check | D9: Locked | E9: Decides on re-checks when a language fails | F9: Draws the random back-translation sample | G9: Nurse reviews flagged items | I9: Independent native check of every guide | K9: Funds checker pay | L9: Spot-reads guides in their language
A10: aid | B10: 4 | C10: Share | D10: Locked | E10: Signs off launch | H10: Builds the app and print cards | I10: Tests on real cheap phones and printouts | J10: Announces in each language | K10: Pays for sample printing | L10: Installs and shares
A11: llm | B11: 1 | C11: Data | D11: Now | E11: Sets the 5-million-word floor per language and decides when the corpus is frozen | F11: Merges the two training squads and lines up which languages get Experts first | G11: Native speakers find licensed sources, fix legacy fonts and write frozen test questions | H11: Builds the cleaning, dedup and tokenizer pipeline | I11: Samples 200 lines per language and audits every licence | J11: Recruits speakers of the rarest languages | K11: Funds the native-speaker hours and the test-run GPUs | L11: Types everyday sentences in their mother tongue
A12: llm | B12: 2 | C12: Train | D12: Locked | E12: Picks the model size and signs the go/no-go for the 64-GPU run | G12: Writes native instruction examples | H12: Sets up the crash-safe training run | I12: Kills a node on purpose and re-runs the evaluation scripts | K12: Covers the GPU booking before it starts
A13: llm | B13: 3 | C13: Test | D13: Locked | E13: Signs the 22-row table, losses included | G13: Grades open-ended answers in their language | H13: Runs the evaluation harness on our model and 2 baselines | I13: Re-runs 10% of the scoring | J13: Explains the scores in plain words
A14: llm | B14: 4 | C14: Ship | D14: Locked | E14: Approves the public release | H14: Builds the 4-bit laptop version | I14: Installs it on their own laptop and times it | J14: Writes the model card in 22 languages | L14: Teachers try it offline in the pilot schools
A15: harness | B15: 1 | C15: Loop | D15: Done | E15: Sets the turn, token and time caps every run must respect | F15: Splits the loop into small jobs and picks the 20 replay quests | H15: Builds the loop and the replay runner | I15: Replays runs and confirms the logs match what happened | K15: Funds the model API bill | L15: Hands real quests to the engine and reports what felt wrong
A16: harness | B16: 2 | C16: Tools | D16: Now | E16: Approves the permission model all tools must follow | F16: Writes when an agent must stop and ask its human | G16: Writes prompt-injection attacks that real pages could carry | H16: Builds each tool inside a sandbox with a manifest | I16: Tries to make the agent spend or write what it shouldn't | J16: Explains the safety model so new builders can join | K16: Pays the model bill for red-team runs | L16: Runs real quests and logs what broke
A17: harness | B17: 3 | C17: Review | D17: Locked | F17: Decides which results skip human review | G17: Writes the planted bad results and the review rubric | H17: Builds the checker agent and the review queue | I17: Reviews the agent's approvals and records every overturn | J17: Publishes the miss rate honestly
A18: harness | B18: 4 | C18: Scale | D18: Locked | E18: Calls the go/no-go on real money | G18: Designs the spend alerts and the failure drills | H18: Builds the load test and the ledger checks | I18: Reconciles the ledger by hand on a sample | K18: Funds the 72-hour run
A19: reef | B19: 1 | C19: Pilot | D19: Done | F19: Picks 200 candidate sites that cover the range of reef types | G19: Labels reef cover on satellite tiles | H19: Builds the tile cutter and the labelling tool | I19: Re-labels 10% of tiles to measure agreement | K19: Funds the labelling quests
A20: reef | B20: 2 | C20: Ground truth | D20: Now | E20: Decides where the last boat money goes | F20: Finds dive shops and books boat days around the weather | G20: Dives, lays transects and photographs quadrats | H20: Matches each site to its satellite pixels | I20: Checks every report against its photos and GPS | J20: Shows why the squad is stuck and recruits divers and Checkers | K20: Pays for boat days | L20: Snorkels shallow reef flats with a colour chart
A21: reef | B21: 3 | C21: Model | D21: Locked | E21: Decides whether 80% is met honestly | G21: Reviews errors and spots depth and water traps | H21: Trains the model | I21: Re-runs the held-back test | J21: Explains what the map can and cannot see
A22: reef | B22: 4 | C22: Public map | D22: Locked | H22: Builds the weekly pipeline and the web map | I22: Spot-checks 20 new tiles each week | J22: Shows rangers how to read it | K22: Covers hosting for the first year | L22: Rangers and fishers use it and report errors
A23: lead | B23: 1 | C23: Records | D23: Locked | E23: Sets the privacy and neutrality rules | F23: Drafts and files the public records request | G23: Reads the inventory and writes the pipe ID guide | H23: Builds the photo form that strips addresses and metadata | I23: Tests the guide on sample photos | J23: Wins the missing backers | K23: Backs the launch | L23: Looks up their own address in the inventory
A24: lead | B24: 2 | C24: Photos | D24: Locked | G24: Handles hard cases (painted or wrapped pipe) | I24: Reviews every photo the agent called | J24: Runs library sign-up nights in low-response blocks | K24: Funds the photo rewards | L24: Photographs the pipe at home
A25: lead | B25: 3 | C25: Map | D25: Locked | E25: Signs off on privacy (minimum block size) | H25: Builds the map | I25: Traces blocks back to source | J25: Explains how to read it | L25: Checks their street
A26: lead | B26: 4 | C26: Replace | D26: Locked | E26: Makes the formal ask | F26: Tracks the plan for 12 months | I26: Confirms the plan covers the lines | J26: Gives public comment | K26: Funds the tracking
A27: tutor | B27: 1 | C27: Curriculum | D27: Done | E27: Sets the 3 grades and 10 countries | F27: Maps each curriculum to shared skills | G27: Teachers supply local maths words | I27: A local teacher verifies each map | K27: Funds teacher time | L27: Parents say which topics their kids struggle with
A28: tutor | B28: 2 | C28: App | D28: Done | E28: Decides features to cut | G28: Translates and checks maths wording | H28: Builds the app and shrinks the model | I28: Tests on real cheap phones | J28: Recruits translators | K28: Buys test phones
A29: tutor | B29: 3 | C29: Pilot | D29: Done | E29: Signs school agreements | F29: Picks pilot and comparison classes | G29: Trains teachers | I29: Audits consent forms and logs | K29: Funds phones and chargers | L29: Teachers and volunteers run the start test
A30: tutor | B30: 4 | C30: Results | D30: Now | E30: Decides how to report misses | F30: Schedules test day | G30: Checks the Kenya test matches the curriculum | H30: Builds the results dashboard | I30: Re-scores and audits results | J30: Writes the report and teacher stories | K30: Funds the final push | L30: Runs the end test in a Kenyan class
A31: benefits | B31: 1 | C31: Schemes | D31: Done | E31: Signs off the final list and settles disputes about rules | F31: Chooses which 50 schemes matter most for poor UP families | G31: Reads government orders and writes each scheme card in plain words | H31: Turns the cards into a searchable sheet the helper can read | I31: Compares every card line by line with the official source
A32: benefits | B32: 2 | C32: Helper | D32: Now | E32: Trains the first village volunteers on the same answers | F32: Maps NGOs and CSCs in Sitapur and Banda for Stage 3 | G32: Writes the answer pack for each language from the checked cards | H32: Builds the WhatsApp flows, voice notes included | I32: Scores test answers and blocks any that ask for ID numbers | J32: Records invitations that recruit volunteers and testers | K32: Funds messaging fees and volunteer travel | L32: Native speakers ask real questions and flag wrong or confusing answers
A33: benefits | B33: 3 | C33: Apply | D33: Locked | E33: Runs CSC and tehsil trips and settles problems with offices | F33: Schedules seeding camps and certificate runs by block | H33: Keeps the family-code tracker that holds no ID numbers | I33: Checks each form's checklist before it is sent | K33: Funds stipends and bus fares | L33: Volunteers sit with families and list missing papers
A34: benefits | B34: 4 | C34: Paid | D34: Locked | E34: Escalates stuck cases through IGRS or RTI | F34: Groups failures by cause and books the bank fixes | G34: Explains DBT failure codes and how to fix each one | I34: Confirms payment with the family, via portal status and passbook | J34: Writes consented stories of families who were paid
A35: candidate | B35: 1 | C35: Collect | D35: Done | E35: Signs off the final count of 310 | F35: Tracks withdrawal dates for each constituency | G35: Spots missing pages and revised affidavits | H35: Scripts the downloads and logs file hashes | I35: Matches every file to the Form 7A list
A36: candidate | B36: 2 | C36: One-pagers | D36: Now | E36: Collects conflict-of-interest declarations and keeps the team neutral | F36: Schedules constituencies so all 310 finish on time | G36: Writes profiles from the affidavit and the case glossary | H36: Builds the OCR pre-fill so writers start from a draft | I36: First check of every figure against the PDF | J36: Recruits Marathi writers and Checkers | K36: Funds the legal review and the translators | L36: Reads profiles on a phone and flags confusing lines
A37: candidate | B37: 3 | C37: Check | D37: Locked | E37: Handles candidate correction requests within 12 hours | F37: Runs the equal-treatment audit across all 310 | G37: Legal read of profiles with criminal cases | H37: Freezes approved profiles and records version history | I37: Second independent check of each profile
A38: candidate | B38: 4 | C38: Share | D38: Locked | E38: Calls the hard stop at the silence period | H38: Runs the pages and the visit counter | I38: Hunts for fake or edited copies and reports them | J38: Writes the neutral share message and the reach plan | L38: Shares the constituency link in groups they belong to
A39: pothole | B39: 1 | C39: Map | D39: Now | E39: Brings rider groups and RWAs on board | F39: Picks wards and fills gaps in coverage | G39: Tags who owns each road | H39: Runs the pin form and builds the ward scoreboard | I39: Removes duplicates and re-visits a random 5% | J39: Makes the 30-second 'how to pin safely' video | K39: Funds pin rewards and hosting | L39: Photos and pins potholes on routes they already take
A40: pothole | B40: 2 | C40: File | D40: Locked | F40: Spreads filing across people so no account is flagged | G40: Routes metro, NHAI and utility-trench pins to the right office | H40: Drafts complaint text with location, landmark and photo | I40: Looks up complaint IDs to confirm they exist | L40: Files drafts from their own Sahaaya login
A41: pothole | B41: 3 | C41: Track | D41: Locked | E41: Chases old complaints with the ward engineer | F41: Queues follow-ups and RTIs | H41: Keeps the scoreboard updating weekly | J41: Presents the scoreboard at ward committee meetings | L41: Reports a pothole that reopens on their route
A42: pothole | B42: 4 | C42: Fixed | D42: Locked | F42: Writes the 90-day ward report | G42: Judges whether a patch is level and lasting | I42: Visits 'closed' complaints and takes after-photos | J42: Shares the results with RWAs and the media | K42: Funds the verification visits
A43: rti | B43: 1 | C43: Pick | D43: Done | E43: Splits 4 districts among 4 district owners | F43: Draws a fair 100-school sample from UDISE+ | G43: Finds the right PIO and appellate officer for each block | H43: Sets up the shared school sheet | I43: Spot-checks 10 UDISE codes | J43: Recruits retired teachers in each district
A44: rti | B44: 2 | C44: Ask | D44: Done | E44: Sets the filing date so all clocks start together | G44: Writes the one-page Hindi request | H44: Prints, posts and logs 100 requests | I44: Matches postal receipts to tracker rows | K44: Funds fees and registered post | L44: Signs requests as a local parent where willing
A45: rti | B45: 3 | C45: Replies | D45: Now | E45: Assigns each late reply to a named owner | F45: Groups 59 appeals into district trips | G45: Files first appeals and drafts second appeals | H45: Keeps the deadline tracker and appeal templates | I45: Codes replies and re-checks 1 in 5 | J45: Writes the Hindi appeal guide and recruits filers | K45: Pays bus fares to offices and Patna | L45: Checks one school's public UDISE+ card
A46: rti | B46: 4 | C46: Visit | D46: Locked | E46: Pairs visitors and books visit days with schools | F46: Turns grant heads into a 12-item checklist | G46: Trains visitors on what each grant should buy | I46: Re-visits 20 schools at random | K46: Funds visit travel | L46: Visits a school and photographs the checklist items
A47: rti | B47: 5 | C47: Report | D47: Locked | E47: Approves publication | G47: Signs off the education-finance reading | H47: Builds the one-page report card template | I47: Runs the 15-day right of reply and checks numbers | J47: Presents cards at School Management Committee meetings | L47: Parents read their school's card and say if it is clear
A48: flood | B48: 1 | C48: Sensors | D48: Now | E48: Wins host OK from CDAs and landowners | F48: Picks candidate and final sites | G48: Pulls flood history and maps who must approve sites | H48: Builds and installs the gauges | I48: Reviews the plan and checks 14 days of readings | J48: Collects residents' flood stories to show where water comes first | K48: Funds hardware before the rains | L48: Marks where their street floods
A49: flood | B49: 2 | C49: Alerts | D49: Locked | G49: Writes and tests alert text in three languages | H49: Builds the threshold rules and SMS pipeline | I49: Measures delivery time on test alerts | J49: Runs sign-up drives at markets and churches | K49: Funds a season of SMS credit | L49: Signs up and gets neighbours to sign up
A50: flood | B50: 3 | C50: Test | D50: Locked | E50: Runs the after-flood review | G50: Re-tunes thresholds | H50: Repairs failed sensors within 48 hours | I50: Compares alert times with flood photos | L50: Photographs the street mark when water arrives
A51: flood | B51: 4 | C51: Hand over | D51: Locked | E51: Negotiates and signs the handover | H51: Trains local technicians | I51: Watches technicians fix a fault alone | J51: Writes the plain manual in English and Yoruba | K51: Funds the 12-month running reserve
A52: renter | B52: 1 | C52: Letters | D52: Now | E52: Recruits volunteer lawyers and sets the letter list | F52: Ranks problems and maps each letter to the right moment | G52: Drafts letters with Georgia citations | H52: Turns drafts into fill-in templates with 3 boxes | I52: Licensed lawyer gives early review | J52: Finds renters to test plain language | K52: Funds lawyer honoraria and translation | L52: Shares a real renter problem
A53: renter | B53: 2 | C53: Check | D53: Locked | E53: Resolves lawyer disagreements | G53: Translates into Spanish and back-checks | I53: Signs off each letter as a Georgia lawyer | K53: Funds honoraria | L53: Reads letters and says what they mean
A54: renter | B54: 3 | C54: Launch | D54: Locked | F54: Writes the decision paths, e.g. 'court date? → legal aid' | H54: Builds the tool | I54: Reviews privacy and accessibility | J54: Writes the help text | L54: Tests on their own phone
A55: renter | B55: 4 | C55: Use | D55: Locked | E55: Runs the follow-up survey | G55: Flags law changes | I55: Verifies reported outcomes on a sample | J55: Shares the tool at tenant meetings | L55: Sends a letter and reports back
A56: fountains | B56: 1 | C56: Map | D56: Done | F56: Splits the city into grid squares | H56: Builds the Overpass dashboard | I56: Re-surveys 10% | J56: Recruits mappers in outer districts | K56: Funds rewards for outer-district squares | L56: Surveys one grid square
A57: fountains | B57: 2 | C57: Report | D57: Done | E57: Meets district offices to agree a format | G57: Finds the right office for each point type and district | H57: Generates report text from the map data | I57: Checks each report has a reference number | L57: Files reports
A58: fountains | B58: 3 | C58: Fixed | D58: Done | E58: Chases slow offices | H58: Updates the map automatically | I58: Confirms photo dates | J58: Shares wins to keep mappers going | L58: Re-visits and photographs running water
A59: ramp | B59: 1 | C59: Design | D59: Done | E59: Runs the final pick | F59: Splits the job into 12 small design tasks | H59: Draws designs and cutting plans | I59: Checks slope, width and sheet fit | L59: Wheelchair users judge what feels usable
A60: ramp | B60: 2 | C60: Test | D60: Done | G60: Woodworker advises on fixes | H60: Builds prototypes | I60: Runs and records load tests | K60: Pays for sheets | L60: Tries ramps in a wheelchair
A61: ramp | B61: 3 | C61: Guide | D61: Done | G61: Translates | I61: Checks the builds match the plan | J61: Writes the picture-first guide | K61: Pays translators | L61: Builds once from the guide only
A62: ramp | B62: 4 | C62: Build | D62: Done | E62: Coordinates country leads | I62: Verifies photos and slope | J62: Shares builds to recruit more | K62: Sponsors sheets for build days | L62: Builds and logs ramps
A63: pumps | B63: 1 | C63: Find | D63: Done | E63: Recruits and trains the 24 volunteers | F63: Splits the 4 blocks into volunteer routes | H63: Builds the offline survey form | I63: Re-checks entries against photos and GPS | L63: Volunteers walk to each pump and run the 20-stroke test
A64: pumps | B64: 2 | C64: Report | D64: Done | E64: Hands the list to PHED Assistant Engineers in person | F64: Batches the list by mechanic area | G64: Sorts pumps by likely fault: washer, pipe or dry bore | I64: Confirms complaint numbers exist | L64: Files complaints on Sampark for their own village
A65: pumps | B65: 3 | C65: Fix | D65: Done | E65: Follows up with PHED every week | F65: Gets panchayats to fund repairs from tied grants | J65: Shares the monthly fix count at block meetings | K65: Funds follow-up travel and caretaker training | L65: Confirms when their village pump gives water again
A66: pumps | B66: 4 | C66: Prove | D66: Done | E66: Hands the data to the district | H66: Exports a clean dataset for PHED | I66: Re-tests fixed pumps after 30 days | J66: Writes the final report | L66: Reports a re-break straight away
A67: air | B67: 1 | C67: Prototype | D67: Done | E67: Decided to switch sensors after the first test failed | G67: Chose the sensor and read the datasheets | H67: Built the boards and firmware | I67: Ran the 48-hour side-by-side test | K67: Funded parts
A68: air | B68: 2 | C68: Pilot | D68: Done | F68: Collected real quotes | H68: Built 4 trial units | I68: Audited the cost sheet | J68: Wrote the honest stop note | L68: Teachers used them for 2 weeks
A69: glio | B69: 6 | C69: Patients | D69: Locked
A70: aid | B70: 5 | C70: Act | D70: Locked
A71: llm | B71: 5 | C71: Use | D71: Locked
A72: lead | B72: 5 | C72: Replaced | D72: Locked
A73: pothole | B73: 5 | C73: Safer | D73: Locked
A74: rti | B74: 6 | C74: Fixed | D74: Locked
A75: renter | B75: 5 | C75: Fixed | D75: Locked

Sheet Squads
A1: Squad ID | B1: Mission ID | C1: Squad | D1: Lead | E1: Plan | F1: The bet | G1: State | H1: People | I1: Agents | J1: Progress | K1: Target | L1: % of path | M1: Open spots | N1: Character | O1: Main blocker | P1: How the plan works | Q1: Strengths | R1: Weaknesses | S1: Raised | T1: Needed | U1: % funded | V1: Roles needed | W1: Relations | X1: Currency | Y1: Your notes
A2: glio-dock | B2: glio | C2: Fold Gang | D2: Priya Nair | E2: Brute-force docking | F2: Test all 1 million molecules on rented computers. Wide net, fast. | G2: Running | H2: 8 | I2: 10 | J2: 4 | K2: 10 | L2: =IFERROR(J2/K2,"") -> 0.4 | M2: 1 Checker | N2: Veterans · fastest squad | P2: 1. Split a 1-million-molecule public library into 4 batches 2. Run each batch on rented cloud computers 3. Checkers re-run a random 20 from each batch 4. Pass the top results to the shortlist review | Q2: Fast, experienced, good tooling. | R2: Wide screens give many false positives; compute is costly. | S2: 52000 | T2: 70000 | U2: =IFERROR(S2/T2,"") -> 0.74285714 | V2: 1 Checker (computational chemistry) | W2: Competes with Wet Hands and Swarm 404 for shortlist slots; shares compute scripts with Swarm 404. | X2: =INDEX(Missions!$J$2:$J$100,MATCH(B2,Missions!$A$2:$A$100,0)) -> $
A3: glio-repurpose | B3: glio | C3: Wet Hands | D3: Ade Bello | E3: Repurpose approved drugs | F3: Screen 2,800 drugs that are already safe in people. | G3: Running | H3: 5 | I3: 7 | J3: 2 | K3: 10 | L3: =IFERROR(J3/K3,"") -> 0.2 | M3: 1 Expert | N3: Careful · low cost | O3: Needs a partner lab slot | P3: 1. Pull the list of about 2,800 approved drugs 2. Screen them against the ranked targets 3. Experts check published evidence on brain reach 4. Get partner-lab quotes for the top picks | Q3: Approved drugs have known human safety, which is the fastest path to a trial. | R3: Small list; waiting on a lab slot. | S3: 31000 | T3: 60000 | U3: =IFERROR(S3/T3,"") -> 0.51666667 | V3: 1 Expert (pharmacology) | W3: Competes with Fold Gang; feeds candidate ideas to Whole Health. | X3: =INDEX(Missions!$J$2:$J$100,MATCH(B3,Missions!$A$2:$A$100,0)) -> $
A4: glio-gen | B4: glio | C4: Swarm 404 | D4: Mo Hassan | E4: Generate new molecules | F4: 200 small agents design brand-new molecules and vote on the best. | G4: Running | H4: 3 | I4: 200 | J4: 1 | K4: 10 | L4: =IFERROR(J4/K4,"") -> 0.1 | M4: 1 Checker | N4: Small and scrappy · mostly agents | O4: Nobody has checked the designs for toxicity | P4: 1. Train a model on public data 2. Agents generate designs and vote 3. Run an automated safety screen; Checkers review the report 4. Send the best to the shortlist review | Q4: Cheap and creative; mostly agents. | R4: No one had checked the designs; new molecules take longest to reach a trial. | S4: 9000 | T4: 25000 | U4: =IFERROR(S4/T4,"") -> 0.36 | V4: 1 Checker (medicinal chemistry) | W4: Competes with Fold Gang; borrows its compute scripts. | X4: =INDEX(Missions!$J$2:$J$100,MATCH(B4,Missions!$A$2:$A$100,0)) -> $
A5: glio-whole | B5: glio | C5: Whole Health | D5: Sana Malik | E5: Diet + drug combos | F5: Pair approved drugs with diets that slow tumours. | G5: Proposed | H5: 4 | I5: 6 | J5: 141 | K5: 150 | L5: =IFERROR(J5/K5,"") -> 0.94 | M5: Anyone | N5: Patient-led | O5: Needs 9 more backers to launch | P5: 1. Review published studies on diet with approved treatments 2. Pick combinations with existing evidence 3. Propose them for the shortlist as research only 4. Work with GBM Families Circle on plain summaries | Q5: Patient-led; low cost. | R5: Weak evidence base; must avoid giving medical advice. | S5: 2100 | T5: 15000 | U5: =IFERROR(S5/T5,"") -> 0.14 | V5: Anyone; 9 more backers to launch | W5: Proposed; would take ideas from Wet Hands. | X5: =INDEX(Missions!$J$2:$J$100,MATCH(B5,Missions!$A$2:$A$100,0)) -> $
A6: aid-first | B6: aid | C6: First Aiders | D6: Maria Santos | E6: Nurses write, agents translate | F6: Nurses pick and write the guides, agents draft translations, native speakers fix them. | G6: Running | H6: 3 | I6: 6 | J6: 14 | K6: 20 | L6: =IFERROR(J6/K6,"") -> 0.7 | M6: 3 Experts (any language) · 2 Checkers | N6: New and keen | P6: 1. Nurses pick 20 topics and write short plain English masters from IFRC 2020. 2. A language lead builds a 30-word glossary for each language. 3. Agents draft all 20 guides; a native speaker fixes them in Weblate. 4. A second native speaker checks; 1 in 10 is back-translated for a nurse to compare. 5. Publish as an offline app and A5 cards under CC BY 4.0. | Q6: Led by a working ER nurse; simple loop that agents speed up a lot. | R6: Only 3 people today; no speakers yet for 30 of the 50 languages. | S6: 6500 | T6: 20000 | U6: =IFERROR(S6/T6,"") -> 0.325 | V6: 3 Experts (native speakers of Hausa, Amharic, Quechua), 2 Checkers (nurse or doctor), 1 Maker (illustrator) | W6: The only squad. Welcomes merges from any translator group. | X6: =INDEX(Missions!$J$2:$J$100,MATCH(B6,Missions!$A$2:$A$100,0)) -> $
A7: llm-base | B7: llm | C7: Bharat Base | D7: Vikram Rao | E7: Train our own from scratch | F7: Build a small model from zero, trained only on Indian text. | G7: Running | H7: 12 | I7: 16 | J7: 9 | K7: 22 | L7: =IFERROR(J7/K7,"") -> 0.40909091 | M7: 2 Experts (Odia, Assamese) · 1 Patron | N7: Veterans · big GPU bill | O7: GPU money runs out in 3 weeks | P7: 1. Run 100M-parameter test models on 8 GPUs to pick the language mix (how much rare-language text to repeat). 2. Freeze a 64k-token shared tokenizer once every script passes the 1.5× token-per-word test. 3. Train one 1–2B model on 64 GPUs with checkpoints every 2 hours so a crash costs little. 4. Instruction-tune on about 2,000 native-written examples per language. 5. Fold in Fine-Tune Force as a second arm: continue training an open base model on the same data, and keep whichever wins in Stage 3. | Q7: Experienced trainers. A from-scratch model means a clean licence and a tokenizer built for Indic scripts from day one. | R7: Biggest GPU bill. A small from-scratch model will reason worse than a tuned larger open model. | S7: 1800000 | T7: 3200000 | U7: =IFERROR(S7/T7,"") -> 0.5625 | V7: 2 Experts (Odia, Assamese), 1 Checker (ML evaluation), 1 Patron | W7: Merging with Fine-Tune Force; fed by Data Desh's cleaned text | X7: =INDEX(Missions!$J$2:$J$100,MATCH(B7,Missions!$A$2:$A$100,0)) -> ₹
A8: llm-tune | B8: llm | C8: Fine-Tune Force | D8: Arnav Singh | E8: Tune an existing open model | F8: Start from a good open model and teach it Indian languages. | G8: Merging | H8: 4 | I8: 5 | J8: 5 | K8: 22 | L8: =IFERROR(J8/K8,"") -> 0.22727273 | M8: — | N8: Merging into Bharat Base | O8: Same data as Bharat Base, so they're joining forces | P8: 1. Start from an open 1–3B model whose licence allows redistribution. 2. Extend its vocabulary with Indic tokens, then continue training it on Data Desh's text. 3. Tested on 5 languages (Hindi, Punjabi, Tamil, Telugu, Urdu): held-out loss fell in all 5. Now joining Bharat Base as its 'tuned' arm. | Q8: Cheap and fast. It inherits reasoning from a stronger base model. | R8: It depends on another model's licence and tokenizer. Rare scripts still break into many tokens unless the vocabulary is extended. | S8: 200000 | T8: 200000 | U8: =IFERROR(S8/T8,"") -> 1 | V8: None; members move to Bharat Base | W8: Merging into Bharat Base; uses the same data as Bharat Base from Data Desh | X8: =INDEX(Missions!$J$2:$J$100,MATCH(B8,Missions!$A$2:$A$100,0)) -> ₹
A9: llm-data | B9: llm | C9: Data Desh | D9: Fatima Sheikh | E9: Best data wins | F9: Spend all effort on clean, checked text. Hand it to whoever trains. | G9: Running | H9: 9 | I9: 8 | J9: 7 | K9: 22 | L9: =IFERROR(J9/K9,"") -> 0.31818182 | M9: 3 Checkers (any Indian language) | N9: Linguists | P9: 1. Paid native-speaker Experts find sources, fix legacy fonts and clean text, about 10,000 lines per quest. 2. Agents run language-ID, deduplication and personal-data stripping. Humans check samples of 200 lines. 3. Keep a licence log line for every source; anything unclear is dropped. 4. Write and freeze native test questions per language before any training. 5. Hand the frozen corpus to whoever trains. | Q9: Linguists who read 6 or more scripts. Their clean data helps every squad. | R9: They do not train, so their payoff depends on Bharat Base finishing. Checkers for rare languages are hard to find. | S9: 650000 | T9: 900000 | U9: =IFERROR(S9/T9,"") -> 0.72222222 | V9: 3 Checkers (any Indian language, especially Bodo, Dogri, Santali) | W9: Feeds Bharat Base and Fine-Tune Force; no competition | X9: =INDEX(Missions!$J$2:$J$100,MATCH(B9,Missions!$A$2:$A$100,0)) -> ₹
A10: har-loop | B10: harness | C10: Loop Lab | D10: Kit Bashford | E10: One strong agent | F10: One capable agent loop with strict limits on money and tools. | G10: Running | H10: 6 | I10: 8 | J10: 6 | K10: 10 | L10: =IFERROR(J10/K10,"") -> 0.6 | M10: 1 Maker · 1 Checker | N10: Veterans | O10: The browser tool sometimes clicks the wrong button | P10: 1. One agent loop with hard caps on turns, tokens, time and money for each quest. 2. Every tool declares a manifest (what it reads, writes and spends) and runs in its own sandbox. 3. Anything outside the manifest pauses and asks the human. 4. Red-team attacks become CI tests; a tool only merges when its tests pass. | Q10: Simple to reason about and audit. One trace per quest. | R10: One agent's mistakes are not caught by anything but the review step. Slow on big quests. | S10: 14000 | T10: 22000 | U10: =IFERROR(S10/T10,"") -> 0.63636364 | V10: 1 Maker (browser automation), 1 Checker (security) | W10: Competes with Small Crew on the loop design; shares the tool manifests and red-team suite with them | X10: =INDEX(Missions!$J$2:$J$100,MATCH(B10,Missions!$A$2:$A$100,0)) -> $
A11: har-crew | B11: harness | C11: Small Crew | D11: Lena Vogt | E11: Many small agents | F11: Lots of small agents that each do one job and check each other. | G11: Running | H11: 4 | I11: 30 | J11: 4 | K11: 10 | L11: =IFERROR(J11/K11,"") -> 0.4 | M11: 1 Planner | N11: Small and scrappy · mostly agents | P11: 1. Split each quest into 12 small jobs, each done by a narrow agent with only the tools that job needs. 2. A planner agent hands out jobs; maker and checker agents never share context. 3. The agent that reads untrusted web text has no access to secrets or payments. 4. Humans see only the final result plus the checker agent's notes. | Q11: Least privilege comes naturally, because each agent holds one permission. Agents check each other. | R11: 30 agents mean a higher model bill and harder debugging. Hand-offs lose context. | S11: 6500 | T11: 12000 | U11: =IFERROR(S11/T11,"") -> 0.54166667 | V11: 1 Planner | W11: Competes with Loop Lab; its checker agent design feeds the Stage 3 review step for both | X11: =INDEX(Missions!$J$2:$J$100,MATCH(B11,Missions!$A$2:$A$100,0)) -> $
A12: reef-ops | B12: reef | C12: Reef Ops | D12: Tomás Reyes | E12: Divers check, satellites scale | F12: Divers score 200 reefs, then the map learns from them. | G12: Stuck | H12: 4 | I12: 5 | J12: 74 | K12: 200 | L12: =IFERROR(J12/K12,"") -> 0.37 | M12: 2 Experts (divers) · 1 Checker | N12: Hands-on | O12: Out of money for dive trips; 30 reports wait for a checker | P12: 1. Divers lay a 50 m transect at each site and photograph 20 quadrats. 2. Photos are annotated in CoralNet for cover classes; colour is scored with the Coral Health Chart. 3. Each site gets GPS, depth and date, then is matched to the nearest cloud-free satellite image. 4. Checkers pass every report before it trains the model. 5. Add snorkel surveys on reef flats to cut the cost per site. | Q12: Real ground truth from trained divers. Results experts will trust. | R12: Expensive and slow, and weather-bound. Stuck at 74 sites with 30 reports unchecked. | S12: 31000 | T12: 52000 | U12: =IFERROR(S12/T12,"") -> 0.59615385 | V12: 2 Experts (certified divers), 1 Checker (marine biology) | W12: Feeds Sky Eyes: their maps can't be trusted without Reef Ops' ground truth | X12: =INDEX(Missions!$J$2:$J$100,MATCH(B12,Missions!$A$2:$A$100,0)) -> $
A13: reef-sky | B13: reef | C13: Sky Eyes | D13: Coral (agent) | E13: Satellite only | F13: Agents read satellite photos, no divers needed. | G13: Running | H13: 0 | I13: 6 | J13: 40 | K13: 200 | L13: =IFERROR(J13/K13,"") -> 0.2 | M13: 1 Checker (any human) | N13: 🤖 Agents only · no human has checked their work | O13: No human checker yet | P13: 1. Agents classify satellite tiles for reef cover and brightening. 2. They compare each tile to sea-temperature heat stress to flag likely bleaching. 3. They produce draft maps for all candidate sites. | Q13: Fast and cheap; covers far more area than divers can. | R13: No human has checked any map, so none of its 40 sites count yet. It can't tell bleached coral from sand without ground truth. | S13: 9000 | T13: 14000 | U13: =IFERROR(S13/T13,"") -> 0.64285714 | V13: 1 Checker (any human) | W13: Competes with Reef Ops on cost; depends on Reef Ops' ground truth to prove itself; likely to become Stage 3's model team | X13: =INDEX(Missions!$J$2:$J$100,MATCH(B13,Missions!$A$2:$A$100,0)) -> $
A14: lead-pipes | B14: lead | C14: Pipe Finders | D14: Bill Turner | E14: Records + home photos | F14: Start from city records, then people photo the pipe at home. | G14: Proposed | H14: 2 | I14: 3 | J14: 96 | K14: 150 | L14: =IFERROR(J14/K14,"") -> 0.64 | M14: Anyone | N14: Proposed · not launched | O14: Needs 54 more backers to launch | P14: 1. Start from the city's public inventory and focus only on 'unknown' lines. 2. Residents do a magnet-and-scratch test and photograph the pipe where it enters the house. 3. An agent makes a first call; a human Checker confirms; a plumber checks 40 random homes. 4. Publish a block-level map and give the data to the city. | Q14: Led by a retired water engineer. Low cost. Works with the city's legal deadline, not against it. | R14: Two people so far. Depends on renters and older blocks taking part. | S14: 9600 | T14: 30000 | U14: =IFERROR(S14/T14,"") -> 0.32 | V14: Anyone; especially 1 Maker (forms/maps), 2 Checkers, 1 Storyteller in Dayton | W14: No competing squad yet | X14: =INDEX(Missions!$J$2:$J$100,MATCH(B14,Missions!$A$2:$A$100,0)) -> $
A15: tutor-chalk | B15: tutor | C15: Chalk Squad | D15: Chioma Okafor | E15: Offline app on cheap phones | F15: One small app that works without internet, tested in real classes. | G15: Running | H15: 7 | I15: 9 | J15: 9 | K15: 10 | L15: =IFERROR(J15/K15,"") -> 0.9 | M15: 1 Checker | N15: One step from winning | O15: Kenya results not in yet | P15: 1. Map 10 curricula to one shared list of skills. 2. Build a small offline app with short exercises and simple hints that runs on a 1–2 GB phone. 3. Pilot in 25 classes: 1 phone per small group, 3 sessions a week for 4 weeks. 4. Give the same 20-minute EGMA-style test before and after, in pilot and comparison classes. 5. Re-check every score and publish all results, good or bad. | Q15: Led by a working head teacher; the app already works; 9 of 10 countries done. | R15: Small samples per country; depends on school calendars; one open Checker spot. | S15: 104000 | T15: 120000 | U15: =IFERROR(S15/T15,"") -> 0.86666667 | V15: 1 Checker (education statistics), 1 User in Nairobi or Kisumu to help run the test | W15: Only squad; may later feed a larger follow-up study run by the partner university. | X15: =INDEX(Missions!$J$2:$J$100,MATCH(B15,Missions!$A$2:$A$100,0)) -> $
A16: ben-haq | B16: benefits | C16: Haq Helpers | D16: Divya Reddy | E16: WhatsApp helper | F16: A WhatsApp helper that answers in 6 languages. | G16: Running | H16: 9 | I16: 12 | J16: 4 | K16: 6 | L16: =IFERROR(J16/K16,"") -> 0.66666667 | M16: 1 Expert (Bhojpuri) · 1 User | N16: Tech-first | P16: 1. Turn the 50 scheme cards into question-and-answer packs 2. A native speaker writes and records each language pack; the agent only drafts 3. Families send a text or voice note; the helper replies with the scheme, the papers and the nearest CSC 4. The helper never asks for ID numbers; hard cases are handed to the nearest village volunteer | Q16: Reaches anyone with WhatsApp, costs little per answer, and every answer traces back to a checked card. | R16: Can't help families without a smartphone, and a wrong answer spreads fast. | S16: 210000 | T16: 350000 | U16: =IFERROR(S16/T16,"") -> 0.6 | V16: 1 Expert (Bhojpuri), 1 User tester (Bundeli) | W16: Feeds Village Volunteers and NGO Bridge with the same checked answers; competes with them on Stage 2 language count. | X16: =INDEX(Missions!$J$2:$J$100,MATCH(B16,Missions!$A$2:$A$100,0)) -> ₹
A17: ben-village | B17: benefits | C17: Village Volunteers | D17: Meera Joshi | E17: One volunteer per village | F17: Train one trusted person in each village to help neighbours. | G17: Running | H17: 14 | I17: 6 | J17: 3 | K17: 6 | L17: =IFERROR(J17/K17,"") -> 0.5 | M17: 2 Leaders (field) | N17: Ground-first | P17: 1. Pick one trusted person per village: a self-help group member, a retired teacher, a ration-shop helper 2. Train them in a half-day session at the panchayat bhawan with paper checklists 3. Each volunteer sits with 25 families and lists missing schemes and papers 4. Volunteers walk families through CSC visits and check forms before they're sent | Q17: Trust. Families open up to a neighbour, and it works without smartphones. | R17: Slow to scale, depends on a few people, and quality varies by volunteer. | S17: 180000 | T17: 400000 | U17: =IFERROR(S17/T17,"") -> 0.45 | V17: 2 Leaders (field, Sitapur and Banda) | W17: Uses Haq Helpers' answers; will likely merge field work with NGO Bridge in Banda. | X17: =INDEX(Missions!$J$2:$J$100,MATCH(B17,Missions!$A$2:$A$100,0)) -> ₹
A18: ben-ngo | B18: benefits | C18: NGO Bridge | D18: Rahul Verma | E18: Work through local NGOs | F18: Partner with NGOs that already help families with forms. | G18: Running | H18: 4 | I18: 5 | J18: 2 | K18: 6 | L18: =IFERROR(J18/K18,"") -> 0.33333333 | M18: 1 Planner | N18: Partnerships | O18: Waiting on 3 NGOs to reply | P18: 1. List NGOs and CSCs in Sitapur and Banda that already help with forms 2. Sign a one-page pledge: free help, no document copies kept 3. Share the checked scheme cards and the helper number 4. Track payments and fix DBT failures with bank branches | Q18: Borrows staff and trust that already exist; strong on banking and DBT fixes. | R18: Waiting on 3 NGOs to reply; each partner has its own priorities. | S18: 60000 | T18: 250000 | U18: =IFERROR(S18/T18,"") -> 0.24 | V18: 1 Planner | W18: Competes with Village Volunteers in Banda; feeds Stage 4 payment tracking for all squads. | X18: =INDEX(Missions!$J$2:$J$100,MATCH(B18,Missions!$A$2:$A$100,0)) -> ₹
A19: cand-clear | B19: candidate | C19: Vote Clear | D19: Arjun Mehta | E19: Plain one-pagers | F19: Turn every affidavit into the same plain one-page profile. | G19: Running | H19: 11 | I19: 14 | J19: 140 | K19: 310 | L19: =IFERROR(J19/K19,"") -> 0.4516129 | M19: 3 Experts (Marathi) · 4 Checkers | N19: Racing a deadline | O19: 12 days to voting day | P19: 1. Download every Form 26 and lock the list against Form 7A 2. OCR pre-fills a draft; a human writes the one-pager with a page reference for every fact 3. First check while writing, then a second independent check, then a 12-hour correction window 4. Publish one page per candidate in ballot order, and share per constituency until the silence period | Q19: One template and one process for everyone, so it's provably neutral. A journalist lead and law-student experts. | R19: Short of Marathi writers and Checkers with 12 days left, and only one squad, so there's no backup if it stalls. | S19: 320000 | T19: 500000 | U19: =IFERROR(S19/T19,"") -> 0.64 | V19: 3 Experts (Marathi), 4 Checkers | W19: The only squad. It borrows second Checkers from other missions' Checker pool to stay independent. | X19: =INDEX(Missions!$J$2:$J$100,MATCH(B19,Missions!$A$2:$A$100,0)) -> ₹
A20: pot-patrol | B20: pothole | C20: Pothole Patrol | D20: Kavya Iyer | E20: Riders pin as they ride | F20: Delivery riders and commuters pin potholes on routes they already take. | G20: Running | H20: 22 | I20: 10 | J20: 1240 | K20: 5000 | L20: =IFERROR(J20/K20,"") -> 0.248 | M20: Anyone with a phone | N20: Big and growing | P20: 1. Riders and commuters pin potholes on routes they already travel, but only when stopped 2. Checkers merge duplicates within 15 m and tag the road owner 3. Agents draft complaints; people file them from their own accounts 4. Follow up at day 15, 30 and 60, then return for an after-photo | Q20: Huge free coverage from people already on the road. Simple quests. | R20: Pins cluster on delivery routes and miss residential lanes. One big squad, so quality varies. | S20: 240000 | T20: 800000 | U20: =IFERROR(S20/T20,"") -> 0.3 | V20: Anyone with a phone; 2 Checkers; 1 Expert (road ownership) | W20: The only squad for now. It may split into one squad per city corporation once filing starts. | X20: =INDEX(Missions!$J$2:$J$100,MATCH(B20,Missions!$A$2:$A$100,0)) -> ₹
A21: rti-watch | B21: rti | C21: School Watch | D21: Rajesh Kumar | E21: File and follow up in person | F21: File every request, and appeal in person when replies are late. | G21: Stuck | H21: 5 | I21: 6 | J21: 41 | K21: 100 | L21: =IFERROR(J21/K21,"") -> 0.41 | M21: 4 people in Bihar (appeals) | N21: Retired teachers + students | O21: 59 late replies need appeals filed in person | P21: 1. Retired teachers in each district own 25 schools each. 2. One standard request goes to every block PIO, filed by registered post with a ₹10 postal order. 3. A shared tracker flags day 30 (reply due), day 60 (file first appeal) and day 90+ (second appeal). 4. Late appeals are grouped by district office so one trip files 5 to 10 appeals and comes back with stamped receipts. 5. Students code replies into a sheet. Two Checkers re-read 1 in 5. | Q21: Retired teachers know how block offices work, speak Hindi and Bhojpuri, and are taken seriously by officials. | R21: Only 5 people, mostly in Patna. Appeals in Gaya and Purnia wait for someone to travel, and Commission hearings need a person in Patna. | S21: 600000 | T21: 600000 | U21: =IFERROR(S21/T21,"") -> 1 | V21: 4 Experts in Bihar for appeals (1 each in Gaya, Muzaffarpur, Purnia, Patna), 2 Checkers to code replies | W21: Only squad on this mission. Its tracker and appeal templates are reused by later squads. | X21: =INDEX(Missions!$J$2:$J$100,MATCH(B21,Missions!$A$2:$A$100,0)) -> ₹
A22: flood-watch | B22: flood | C22: Flood Watch | D22: Femi Adeyemi | E22: Sensors + text alerts | F22: Cheap river sensors that text families when water rises fast. | G22: Waiting for OK | H22: 3 | I22: 4 | J22: 0 | K22: 20 | L22: =IFERROR(J22/K22,"") -> 0 | M22: 1 Maker | N22: New | O22: Plan waits for the creator's OK | P22: 1. Map where water comes first, from residents' reports and OpenStreetMap. 2. Build ESP32 gauges with ultrasonic sensors, solar power and a 2G/4G modem. They report every 10 minutes. 3. Mount gauges on bridges and walls above the record flood line, with community OK. 4. When a reading crosses its site threshold, send an SMS to opted-in phones in the language each person chose. 5. Tune thresholds after every real flood, then hand over to the CDA and LCDA. | Q22: Femi knows SMS systems from telecom work and lives on a street that floods. Low-cost open hardware. | R22: Only 3 people, no hydrologist yet, and no deal with a local body to take over. | S22: 0 | T22: 25000 | U22: =IFERROR(S22/T22,"") -> 0 | V22: 1 Maker (electronics), 1 Expert (hydrology), 1 Leader with CDA contacts | W22: Only squad. Its open hardware and alert text can feed later squads in other cities. | X22: =INDEX(Missions!$J$2:$J$100,MATCH(B22,Missions!$A$2:$A$100,0)) -> $
A23: renter-right | B23: renter | C23: Rent Right | D23: Jamal Carter | E23: Templates checked by lawyers | F23: 10 letters that cover most problems, each checked by a lawyer. | G23: Raising money | H23: 3 | I23: 4 | J23: 4 | K23: 10 | L23: =IFERROR(J23/K23,"") -> 0.4 | M23: 1 Patron · 1 Checker (lawyer) | N23: Small | O23: $3,200 of $8,000 raised | P23: 1. Ask renters which problems hit most and rank the top 10. 2. Draft one letter per problem, citing the exact Georgia section. 3. Lawyers review early and then sign off formally. Spanish versions are back-checked. 4. A phone tool asks 3 questions and fills the letter. The tenant sends it by certified mail. 5. Anything with a court date goes straight to a legal aid referral. | Q23: Jamal knows renters and their real problems. 4 letters already drafted. | R23: No lawyer on the squad yet. Only $3,200 of $8,000 raised. | S23: 3200 | T23: 8000 | U23: =IFERROR(S23/T23,"") -> 0.4 | V23: 1 Patron, 1 Checker (Georgia-licensed lawyer), 1 Expert (Spanish) | W23: Only squad. Will refer court cases to the legal aid clinic partner. | X23: =INDEX(Missions!$J$2:$J$100,MATCH(B23,Missions!$A$2:$A$100,0)) -> $
A24: fnt-crew | B24: fountains | C24: Small Crew | D24: Lena Vogt | E24: Grid squares + one report format | F24: Split Berlin into small squares anyone can finish in an hour, and send every office the same clean report. | G24: Won | L24: =IFERROR(J24/K24,"") | P24: 1. Split Berlin into 120 squares of about 2 × 2 km on a shared map. 2. Each player claims a square and surveys it with StreetComplete. 3. A dashboard shows empty squares. Outer squares pay more. 4. A script turns broken points into one German report per office. 5. Re-visit after each fix and update OSM. | Q24: Small, fast jobs. Clear data. Good relations with district offices. | R24: Outer districts were slow. Fixes depended on district budgets. | S24: 12000 | T24: 12000 | U24: =IFERROR(S24/T24,"") -> 1 | V24: None (finished) | W24: Only squad. Its open data is now used by other city water-map projects. | X24: =INDEX(Missions!$J$2:$J$100,MATCH(B24,Missions!$A$2:$A$100,0)) -> $
A25: ramp-crew | B25: ramp | C25: Small Crew | D25: Lena Vogt | E25: One sheet, many hands | F25: Split the design into 12 small jobs, test hard, then let people build it everywhere. | G25: Won | L25: =IFERROR(J25/K25,"") | P25: 1. Set clear rules: 1:12, 800 mm wide, one sheet 2. 12 people each draw a design; Checkers filter 3. Build and load-test 10 copies 4. Write a picture-first guide and translate it 5. Run build days and check photos | Q25: Small jobs let 85 players help; strict testing. | R25: Only fits one step; plywood costs vary. | S25: 15000 | T25: 15000 | U25: =IFERROR(S25/T25,"") -> 1 | V25: None (finished) | W25: Only squad. Its design was later forked by local groups for longer ramps. | X25: =INDEX(Missions!$J$2:$J$100,MATCH(B25,Missions!$A$2:$A$100,0)) -> $
A26: pump-crew | B26: pumps | C26: Pump Watch | D26: Sunita Devi | E26: One volunteer per gram panchayat | F26: Local women who already walk to the pumps can report them better than any outside survey team. | G26: Won | L26: =IFERROR(J26/K26,"") | P26: 1. Train one volunteer per panchayat to run the 20-stroke test and log symptoms 2. Survey every pump offline and sync in town 3. Hand the broken list to PHED block offices and file on Sampark 4. Follow up weekly; ask panchayats to fund repairs stuck for parts; re-check after 30 days | Q26: Local trust and knowledge, low cost, and data PHED could actually use. | R26: Heat and distance slowed the survey; the squad depended on PHED stock for parts. | S26: 400000 | T26: 400000 | U26: =IFERROR(S26/T26,"") -> 1 | V26: Filled: 24 volunteers, 4 Checkers, 1 Planner | W26: The only squad. It shared its field method with the benefits mission's Village Volunteers. | X26: =INDEX(Missions!$J$2:$J$100,MATCH(B26,Missions!$A$2:$A$100,0)) -> ₹
A27: air-crew | B27: air | C27: Fresh Air Crew | D27: Sofia Rossi | E27: Cheapest sensor that's still honest | F27: A simple, open sensor with a traffic-light display can hit $20 at 50 units. | G27: Stopped | L27: =IFERROR(J27/K27,"") | P27: 1. Test accuracy first against a reference meter 2. Cost a 50-unit batch from real quotes 3. Pilot in 10 classrooms 4. Stop and refund if the price can't be met | Q27: Clear numbers and an honest stop rule. Good accuracy testing. | R27: Didn't get real batch quotes before starting. | S27: 18000 | T27: 18000 | U27: =IFERROR(S27/T27,"") -> 1 | V27: None (finished) | W27: Solo squad | X27: =INDEX(Missions!$J$2:$J$100,MATCH(B27,Missions!$A$2:$A$100,0)) -> $
A28: aid-cpr | B28: aid | C28: Pulse Club | D28: Grace Mensah | E28: CPR in every school | F28: Teach every 12-year-old CPR. Kids teach their families. | G28: Proposed | H28: 3 | I28: 3 | J28: 0 | L28: =IFERROR(J28/K28,"") | M28: 1 Leader, 2 Experts | N28: Teachers · new | O28: Needs one school to say yes | P28: 1. Write a 45-minute CPR lesson a teacher can run 2. Pilot it in one school 3. Each pupil teaches 2 family members 4. Count who can still do it 3 months later | Q28: Reaches whole families through kids. | R28: Slow to scale; needs schools to agree. | S28: 600 | T28: 8000 | U28: =IFERROR(S28/T28,"") -> 0.075 | V28: 1 Expert (resuscitation trainer) | W28: Competes with First Aiders; can use their guides | X28: =INDEX(Missions!$J$2:$J$100,MATCH(B28,Missions!$A$2:$A$100,0)) -> $
A29: aid-line | B29: aid | C29: Line Lift | D29: Tunde Bakare | E29: A helper on the phone | F29: A free number where a trained volunteer talks you through it until help comes. | G29: Proposed | H29: 2 | I29: 4 | J29: 0 | L29: =IFERROR(J29/K29,"") | M29: 2 Experts, 1 Checker | N29: Night owls | O29: Needs trained volunteers for nights | P29: 1. Pick one city and one language 2. Train 20 volunteers with the guides 3. Run the line for 4 weeks 4. Check every call log | Q29: Works for people who can't read. | R29: Needs people awake around the clock. | S29: 0 | T29: 15000 | U29: =IFERROR(S29/T29,"") -> 0 | V29: 2 Experts (nurses), 1 Checker | W29: Uses First Aiders' guides as its script | X29: =INDEX(Missions!$J$2:$J$100,MATCH(B29,Missions!$A$2:$A$100,0)) -> $
A30: lead-filter | B30: lead | C30: Filter First | D30: Rosa Delgado | E30: Filters while pipes wait | F30: Get a certified filter into every home with kids now, while the pipes wait their turn. | G30: Proposed | H30: 2 | I30: 2 | J30: 0 | L30: =IFERROR(J30/K30,"") | M30: 1 Planner, 1 Storyteller | N30: Fast · practical | O30: Needs filter money | P30: 1. Find homes with kids on suspected lead lines 2. Hand out certified filters with a 1-page guide 3. Check filters are used after 30 days | Q30: Protects kids this month, not in 5 years. | R30: Filters need changing; doesn't remove the pipe. | S30: 300 | T30: 6000 | U30: =IFERROR(S30/T30,"") -> 0.05 | V30: 1 Planner, 1 Storyteller | W30: Works next to Pipe Finders and uses their map | X30: =INDEX(Missions!$J$2:$J$100,MATCH(B30,Missions!$A$2:$A$100,0)) -> $
A31: tutor-front | B31: tutor | C31: Front Row | D31: Wanjiru Kamau | E31: Help the teacher, not the phone | F31: Give teachers a 10-minute daily routine that finds who is behind and helps them catch up. | G31: Proposed | H31: 2 | I31: 2 | J31: 0 | L31: =IFERROR(J31/K31,"") | M31: 1 Expert, 1 Maker | N31: Teachers | O31: Needs a class to try it | P31: 1. Write a 10-minute daily check 2. Group kids by what they can do, not their age 3. Try it for 4 weeks in one class 4. Compare with Chalk Squad's test | Q31: No phones needed; teachers already there. | R31: Busy teachers may drop it. | S31: 0 | T31: 4000 | U31: =IFERROR(S31/T31,"") -> 0 | V31: 1 Expert (primary teacher) | W31: Competes with Chalk Squad; same end test | X31: =INDEX(Missions!$J$2:$J$100,MATCH(B31,Missions!$A$2:$A$100,0)) -> $
A32: cand-talk | B32: candidate | C32: Chai Charcha | D32: Sneha Kulkarni | E32: Read it out where people meet | F32: Read the one-pagers aloud at chai stalls and housing societies. People trust a face more than a link. | G32: Proposed | H32: 2 | I32: 1 | J32: 0 | L32: =IFERROR(J32/K32,"") | M32: 2 Storytellers | N32: Local · talkative | O32: Needs Vote Clear's checked profiles | P32: 1. Take checked one-pagers only 2. Read every candidate in a seat, same order, no comments 3. Log how many people listened | Q32: Reaches people who don't read PDFs. | R32: Slow; must stay strictly neutral. | S32: 0 | T32: 50000 | U32: =IFERROR(S32/T32,"") -> 0 | V32: 2 Storytellers (Marathi) | W32: Builds on Vote Clear's profiles | X32: =INDEX(Missions!$J$2:$J$100,MATCH(B32,Missions!$A$2:$A$100,0)) -> ₹
A33: pot-crash | B33: pothole | C33: Crash Map | D33: Imran Pasha | E33: Worst first | F33: Start where riders actually crash, not where potholes are. Fix those first. | G33: Proposed | H33: 3 | I33: 2 | J33: 0 | L33: =IFERROR(J33/K33,"") | M33: 1 Expert, 1 Maker | N33: Data people | O33: Needs crash records by road | P33: 1. Gather public crash reports by road 2. Match them to pinned potholes 3. Push the top 100 to the front of the queue | Q33: Fixes what hurts people first. | R33: Crash data is patchy. | S33: 0 | T33: 120000 | U33: =IFERROR(S33/T33,"") -> 0 | V33: 1 Expert (road safety) | W33: Feeds Pothole Patrol's filing order | X33: =INDEX(Missions!$J$2:$J$100,MATCH(B33,Missions!$A$2:$A$100,0)) -> ₹
A34: rti-parents | B34: rti | C34: Parent Panel | D34: Anita Kumari | E34: Parents ask at the school | F34: Help parents on School Management Committees read the school's own accounts at their meetings. | G34: Proposed | H34: 2 | I34: 1 | J34: 0 | L34: =IFERROR(J34/K34,"") | M34: 1 Expert, 1 Storyteller | N34: Parents | O34: Needs committee members willing to try | P34: 1. Make a one-page guide to the school grant 2. Train 10 committee parents 3. They ask at the next meeting and note the answers | Q34: Parents are there every week; RTIs take months. | R34: Parents may not feel safe asking. | S34: 0 | T34: 40000 | U34: =IFERROR(S34/T34,"") -> 0 | V34: 1 Expert (school grants) | W34: Uses School Watch's replies | X34: =INDEX(Missions!$J$2:$J$100,MATCH(B34,Missions!$A$2:$A$100,0)) -> ₹
A35: flood-street | B35: flood | C35: Street Watch | D35: Bisi Adewale | E35: Street captains | F35: One trained captain per street who warns neighbours by phone and loudspeaker. | G35: Proposed | H35: 2 | I35: 1 | J35: 0 | L35: =IFERROR(J35/K35,"") | M35: 1 Leader, 1 Storyteller | N35: Neighbours | O35: Needs captains on 20 streets | P35: 1. Find one captain per flood-prone street 2. Teach the 3 warning signs 3. Practise one warning drill a month | Q35: Works when phones are off or out of credit. | R35: Depends on one person per street. | S35: 0 | T35: 6000 | U35: =IFERROR(S35/T35,"") -> 0 | V35: 1 Leader (community) | W35: Can carry Flood Watch's alerts the last 100 metres | X35: =INDEX(Missions!$J$2:$J$100,MATCH(B35,Missions!$A$2:$A$100,0)) -> $
A36: renter-block | B36: renter | C36: Block by Block | D36: Keisha Brown | E36: Renters act together | F36: All the renters in one building ask together. Landlords answer a group faster. | G36: Proposed | H36: 2 | I36: 1 | J36: 0 | L36: =IFERROR(J36/K36,"") | M36: 1 Leader, 1 Expert | N36: Organisers | O36: Needs one building to start | P36: 1. Pick one building with many repair problems 2. Hold one meeting 3. Send one group letter 4. Follow up together | Q36: Harder to ignore than one renter. | R36: People fear being pushed out. | S36: 0 | T36: 5000 | U36: =IFERROR(S36/T36,"") -> 0 | V36: 1 Expert (tenant law) | W36: Uses Rent Right's letters | X36: =INDEX(Missions!$J$2:$J$100,MATCH(B36,Missions!$A$2:$A$100,0)) -> $

Sheet Quests
A1: Quest ID | B1: Mission ID | C1: Squad ID | D1: Quest | E1: Role | F1: Size | G1: Reward | H1: Currency | I1: State | J1: Where | K1: Safety note | L1: Stage # | M1: Good for you if… | N1: Brief | O1: Steps | P1: You hand in | Q1: Done when | R1: How it's checked | S1: Your agent does | T1: You do | U1: Tools & data | V1: Skills | W1: Depends on | X1: Decision mid-quest | Y1: Options | Z1: Your notes
A2: g12 | B2: glio | C2: glio-repurpose | D2: Catalogue 10 open brain tumour datasets | E2: Expert | F2: M | G2: 60 | H2: $ | I2: Done | J2: Online | L2: 1 | M2: Good for you if you work with biomedical data | N2: We needed a list of what data exists and who may use it. | O2: 1. Search public portals 2. Record link, size and licence 3. Note access rules 4. Add to the catalogue | P2: 10 catalogue rows | Q2: Every field filled | R2: 2 Checkers verify links and licences | S2: Searches portals and fills fields | T2: Judges relevance and licence | U2: GDC portal, CGGA, DepMap | V2: Research data literacy
A3: g13 | B3: glio | C3: glio-gen | D3: Re-check citations for the top 20 targets | E3: Checker | F3: M | G3: 60 | H3: $ | I3: Done | J3: Online | L3: 2 | M3: Good for you if you can read scientific papers | N3: The ranking is only as good as its sources. | O3: 1. Open each cited source 2. Confirm it says what we claim 3. Mark weak or missing evidence | P3: Citation check sheet | Q3: All 20 marked | R3: Second Checker samples 5 | S3: Fetches sources | T3: Judges evidence | U3: Open Targets, PubMed | V3: Reading papers | W3: g12
A4: g7 | B4: glio | C4: glio-repurpose | D4: Pull the list of approved drugs | E4: Expert | F4: S | G4: 10 | H4: $ | I4: Done | J4: Online | L4: 3 | M4: Good for you if you like clean data | N4: Wet Hands starts from drugs already approved for people. | O4: 1. Download public approved-drug lists 2. Remove duplicates 3. Record source and date | P4: Clean list (about 2,800) | Q4: Duplicates removed; source logged | R4: 1 Checker | S4: Merges lists | T4: Checks edge cases | U4: Public approved-drug lists | V4: Data cleaning | W4: g13
A5: g5 | B5: glio | C5: glio-dock | D5: Write this week's progress post | E5: Storyteller | F5: S | G5: 10 | H5: $ | I5: Done | J5: Online | L5: 3 | M5: Good for you if you write clearly | N5: Patients and backers follow along. | O5: 1. Collect squad updates 2. Write 200 plain words 3. Post | P5: Post link | Q5: Published | R5: 1 Checker for accuracy | S5: Drafts from updates | T5: Makes it honest and clear | U5: Blog | V5: Writing
A6: g6c | B6: glio | C6: glio-dock | D6: Launch and monitor compute batch 3 of 4 | E6: Maker | F6: S | G6: 40 | H6: $ | I6: Open | J6: Online | L6: 3 | M6: Good for you if you can run Python jobs in the cloud | N6: Batch 3 of the million-item screen. Mostly launching and watching jobs. | O6: 1. Launch jobs with the squad's scripts 2. Watch for failures 3. Restart failed jobs 4. Upload results | P6: Results file + job log | Q6: All 250,000 processed or logged as failed | R6: g3 Checker re-runs 20 | S6: Launches and monitors jobs | T6: Handles failures and costs | U6: Cloud credits, squad scripts | V6: Python, cloud computing | W6: g7 | X6: Spot prices doubled mid-batch. What do you do? | Y6: Pause and wait | Finish on regular machines | Ask the Leader
A7: g3 | B7: glio | C7: glio-dock | D7: Check 20 docking results from Fold Gang | E7: Checker | F7: S | G7: 25 | H7: $ | I7: Open | J7: Online | L7: 3 | M7: Good for you if you've run docking software before | N7: Every result is re-run before it counts. | O7: 1. Draw 20 at random 2. Re-run with the same settings 3. Compare scores 4. Log mismatches | P7: Re-run log | Q7: 18 of 20 match within tolerance, or the batch is flagged | R7: Second Checker reviews the log | S7: Re-runs jobs | T7: Judges mismatches | U7: Squad scripts | V7: Computational chemistry basics | W7: g6c | X7: 5 of 20 don't match. What now? | Y7: Flag the whole batch | Re-run 20 more
A8: g8 | B8: glio | C8: glio-repurpose | D8: Check which of 40 drugs can reach the brain | E8: Expert | F8: M | G8: 60 | H8: $ | I8: Open | J8: Online | L8: 3 | M8: Good for you if you studied pharmacology | N8: A drug that can't reach the brain won't help. This is a review of published evidence. | O8: 1. Find published evidence for each drug 2. Mark yes, no or unknown 3. Cite sources | P8: 40-row evidence table | Q8: Every row has a source or 'unknown' | R8: Dr. Wei Lin + 1 Checker | S8: Searches literature | T8: Judges evidence | U8: PubMed, drug labels | V8: Pharmacology | W8: g7 | X8: Evidence for one drug conflicts. Mark it? | Y8: Unknown | Yes, with a note
A9: g9 | B9: glio | C9: glio-gen | D9: Train a model on known tumour drugs | E9: Maker | F9: M | G9: 80 | H9: $ | I9: Open | J9: Online | L9: 3 | M9: Good for you if you train ML models | N9: Swarm 404's generator needs a model trained on public data. | O9: 1. Pull the public training set 2. Split train and test 3. Train 4. Report metrics | P9: Model + metrics report + code | Q9: Metrics reproducible by a Checker | R9: 1 Checker re-trains | S9: Writes training code | T9: Judges data quality | U9: ChEMBL, Python | V9: Machine learning | W9: g13
A10: g10 | B10: glio | C10: glio-gen | D10: Review the safety-screen report for 5,000 designs | E10: Checker | F10: S | G10: 20 | H10: $ | I10: Open | J10: Online | L10: 3 | M10: Good for you if you're a trained chemist | N10: Nobody has reviewed Swarm 404's designs. An automated screen ran; a human must review its report. | O10: 1. Read the report summary 2. Sample 50 flagged and 50 passed 3. Agree or disagree 4. Escalate doubts to an Expert | P10: Review note | Q10: 100 sampled and judged | R10: Yuki Mori | S10: Draws the sample | T10: Judges | U10: Screen report | V10: Medicinal chemistry | W10: g9
A11: g17 | B11: glio | C11: glio-dock | D11: Set the rule for choosing the final 10 | E11: Leader | F11: S | G11: 30 | H11: $ | I11: Open | J11: Online | L11: 3 | M11: Good for you if people trust your fairness | N11: Three squads compete for 10 slots; the rule must be fair. | O11: 1. Draft criteria 2. Get each squad's input 3. Get 2 Checkers to agree 4. Publish | P11: Published rule | Q11: All squads acknowledge | R11: 2 Checkers | S11: Drafts options | T11: Decides | U11: Squad results | V11: Leadership | W11: g3, g8, g10 | X11: Should each squad get a guaranteed slot? | Y11: Yes, 2 each | No, best evidence wins
A12: g18 | B12: glio | C12: glio-repurpose | D12: Get 3 quotes from partner labs | E12: Planner | F12: M | G12: 60 | H12: $ | I12: Open | J12: Online | L12: 3 | M12: Good for you if you've managed vendor quotes | N12: Wet Hands is blocked on a lab slot. Quotes now save months. | O12: 1. Write a short request 2. Contact 3 accredited labs 3. Compare price, time and data terms 4. Recommend one | P12: Quote comparison | Q12: 3 quotes in hand | R12: Leader | S12: Drafts emails and the comparison | T12: Negotiates | U12: Email | V12: Procurement | W12: g8 | X12: The cheapest lab won't publish raw data. Accept? | Y12: No, open data is a rule | Negotiate
A13: g20 | B13: glio | C13: glio-gen | D13: Recruit a chemistry Checker for Swarm 404 | E13: Storyteller | F13: S | G13: 15 | H13: $ | I13: Open | J13: Online | L13: 3 | M13: Good for you if you know science communities | N13: Swarm 404's blocker is missing reviewers. | O13: 1. Write a short call 2. Post in public communities 3. Screen replies | P13: 1 signed-up Checker | Q13: Checker joins and passes a test quest | R13: Yuki Mori | S13: Drafts the call | T13: Posts and screens | U13: Sign-up link | V13: none
A14: g19 | B14: glio | C14: glio-whole | D14: Read the progress post and ask 3 questions | E14: User | F14: S | G14: 10 | H14: $ | I14: Open | J14: Online | L14: 3 | M14: Good for you if you're new to science | N14: Patients and families should understand what we do. | O14: 1. Read the latest post 2. Ask 3 questions 3. Mark anything confusing | P14: 3 questions | Q14: Posted | R14: Storyteller answers | S14: Explains terms | T14: Reads and asks | U14: Phone | V14: none | W14: g5
A15: glio-whole-back | B15: glio | C15: glio-whole | D15: Back Whole Health | E15: Patron | F15: S | G15: 0 | H15: $ | I15: Open | J15: Online | L15: 3 | M15: Good for you if you want patient-led research | N15: Whole Health needs 9 more backers to launch. | O15: 1. Read the plan 2. Back it | P15: Backing receipt | Q15: Recorded | R15: Automatic | S15: Summarises the plan | T15: Decides | U15: Wallet | V15: none
A16: g11 | B16: glio | C16: glio-repurpose | D16: Book the partner lab run and sign its budget | E16: Planner | F16: M | G16: 120 | H16: $ | I16: Locked | J16: Online | L16: 4 | M16: Good for you if you're good with contracts | N16: Turns the chosen quote into a booked slot, a budget and shipping paperwork. | O16: 1. Confirm the slot 2. Get the budget approved 3. Arrange shipping and transfer paperwork 4. Share the timeline | P16: Signed booking + budget + paperwork | Q16: Lab confirms in writing | R16: Leader + 1 Checker | S16: Drafts paperwork | T16: Signs and confirms | U16: Contract templates | V16: Project admin | W16: g18, g17 | X16: The slot is 3 months later than planned. Accept? | Y16: Accept | Try the second lab
A17: g15 | B17: glio | C17: glio-repurpose | D17: Hire a regulatory consultant and plan the filing | E17: Leader | F17: M | G17: 100 | H17: $ | I17: Locked | J17: Online | L17: 5 | M17: Good for you if you've worked with regulators | N17: A sponsor needs a clear package. | O17: 1. Shortlist consultants 2. Agree scope and fee 3. Plan the package | P17: Signed scope + plan | Q17: Sponsor agrees to the plan | R17: Mission creator | S17: Compares options | T17: Decides | U17: FDA meeting guidance | V17: Leadership | W17: g11
A18: a6 | B18: aid | C18: aid-first | D18: Agree which guidelines our guides follow | E18: Planner | F18: M | G18: 60 | H18: $ | I18: Done | J18: Online | L18: 1 | M18: Good for you if you know first-aid guidelines | N18: If every nurse writes from a different source, guides will contradict each other. We picked one main source and a rule for conflicts. | O18: 1. List candidate guideline sources 2. Check each licence 3. Pick one main source and one backup 4. Write a one-page conflict rule | P18: One-page 'Sources and rules' doc | Q18: Signed off by 2 nurses | R18: 2 nurse Checkers | S18: Summarises each guideline and its licence | T18: Decides which source we trust | U18: IFRC 2020 guidelines, CC licence texts | V18: First-aid training
A19: a1 | B19: aid | C19: aid-first | D19: Suggest 3 guides and say why they matter | E19: Expert | F19: S | G19: 15 | H19: $ | I19: Open | J19: Online | L19: 1 | M19: Good for you if you have nursing or first-aid experience | N19: We have 14 of 20 guides. We need the last 6, chosen by how often the emergency happens and how much a bystander can help. | O19: 1. Read the current list of 14 2. Propose 3 new topics 3. For each, say how common it is where you live 4. Say what a bystander can do in the first 5 minutes | P19: 3 short entries in the topic form | Q19: Each entry names the emergency, who it hits and the bystander action | R19: 1 nurse Checker | S19: Finds public numbers on how common each emergency is | T19: Picks topics from real experience | U19: Topic form, WHO fact sheets | V19: Some first-aid or health experience | W19: a6 | X19: Snake bites are common where you live but rare elsewhere. Suggest it? | Y19: Yes, as a regional guide | No, keep to universal topics
A20: a2 | B20: aid | C20: aid-first | D20: Pilot: translate the burns guide into Tagalog | E20: Expert | F20: S | G20: 15 | H20: $ | I20: Open | J20: Online | L20: 1 | M20: Good for you if you speak Tagalog | N20: Before doing 1,000 translations we test the loop on one guide. Tagalog first because our lead nurse can review it. | O20: 1. Open the agent draft in Weblate 2. Fix wording so a parent understands it 3. Use glossary terms 4. Time yourself and note hard words | P20: Fixed Tagalog burns guide + a list of hard words + time taken | Q20: Reads naturally to a second Tagalog speaker; no medical step changed | R20: 1 Checker who speaks Tagalog + lead nurse | S20: Drafts the translation and flags low-confidence lines | T20: Fixes meaning and tone | U20: Weblate, glossary | V20: Native Tagalog | W20: a6 | X20: The common local word for a burn remedy implies applying something. Use it? | Y20: Use the plain word for 'cool with water' | Use the local word with a warning
A21: a3 | B21: aid | C21: aid-first | D21: Pilot: check the Spanish choking guide for mistakes | E21: Checker | F21: S | G21: 15 | H21: $ | I21: Open | J21: Online | L21: 1 | M21: Good for you if you speak Spanish | N21: Second half of the pilot: a separate person checks a finished translation so we learn how long a check takes. | O21: 1. Read the English master 2. Read the Spanish version line by line 3. Mark any change in meaning 4. Back-translate 3 key lines to English | P21: Checked guide with comments + 3 back-translated lines | Q21: Every line marked OK or fixed | R21: Lead nurse spot-checks the back-translation | S21: Lines up master and translation side by side | T21: Judges meaning and safety | U21: Weblate review mode | V21: Native Spanish | W21: a6
A22: a4 | B22: aid | C22: aid-first | D22: Draw simple pictures for the CPR guide | E22: Maker | F22: M | G22: 60 | H22: $ | I22: Open | J22: Online | L22: 1 | M22: Good for you if you can draw simple pictures | N22: Pictures carry the guide when reading is hard. This sets the style for all 20 guides. | O22: 1. Read the CPR master 2. Sketch 4–6 panels with no words 3. Use neutral, varied skin tones and clothes 4. Export as SVG | P22: 4–6 SVG panels + style note | Q22: 3 testers who did not read the text describe the steps correctly | R22: Lead nurse + 1 Checker | S22: Suggests panel layout from the text | T22: Draws and judges clarity | U22: Any vector tool | V22: Illustration | W22: a6 | X22: Show the hand position close-up or the whole scene? | Y22: Close-up | Whole scene | Both in two panels
A23: a5 | B23: aid | C23: aid-first | D23: Find 5 people who speak a language we don't have | E23: Storyteller | F23: S | G23: 10 | H23: $ | I23: Open | J23: Online | L23: 1 | M23: Good for you if you are in online groups for a less common language | N23: 30 of our 50 languages have no speaker yet. Recruiting now stops Stage 2 from stalling. | O23: 1. Pick a language from the missing list 2. Post the call in public groups for that language 3. Explain the pay and time 4. Send sign-up links | P23: 5 sign-ups with their language | Q23: 5 new players join and pass a 5-line sample test | R23: Language lead reviews samples | S23: Drafts the call in the target language | T23: Posts and answers questions | U23: Missing-language list, sign-up link | V23: none
A24: a7 | B24: aid | C24: aid-first | D24: Back First Aiders | E24: Patron | F24: S | G24: 0 | H24: $ | I24: Open | J24: Online | L24: 1 | M24: Good for you if you want to fund translators | N24: Backing pays native-speaker checkers in small languages. | O24: 1. Read the plan 2. Choose an amount 3. Back the squad | P24: Backing receipt | Q24: Backing recorded | R24: Automatic | S24: Summarises the plan and budget | T24: Decides to back | U24: In-app wallet | V24: none
A25: a15 | B25: aid | C25: aid-first | D25: Freeze the final list of 20 guides | E25: Leader | F25: M | G25: 50 | H25: $ | I25: Open | J25: Online | L25: 1 | M25: Good for you if you like making the final call | N25: Debate must end so translation can start. The Leader picks the last 6 from the suggestions and records why. | O25: 1. Collect all a1 suggestions 2. Score each on how common and how much a bystander can help 3. Pick 6 and post reasons 4. Lock the list | P25: Final list of 20 with one-line reasons | Q25: 2 nurses agree and the list is locked | R25: 2 nurse Checkers | S25: Tallies suggestions and scores | T25: Makes the final call | U25: Topic form results | V25: Leading a team; first-aid knowledge | W25: a1 | X25: Two good topics tie for the last slot. What now? | Y25: Pick the more common one | Merge them into one guide | Ask the squad to vote
A26: a16 | B26: aid | C26: aid-first | D26: Plan the 50 languages in three waves | E26: Planner | F26: M | G26: 60 | H26: $ | I26: Open | J26: Online | L26: 1 | M26: Good for you if you like spreadsheets and plans | N26: Languages with speakers ready go first, so work never sits waiting. | O26: 1. Use pilot times from a2 and a3 2. List languages by speakers signed up 3. Split into 3 waves 4. Set dates and pay per wave | P26: Wave plan sheet | Q26: Every language has a wave, a lead or an open call | R26: Mission creator | S26: Builds the sheet from sign-up data | T26: Sets priorities | U26: Spreadsheet | V26: Planning | W26: a2, a3, a5
A27: a17 | B27: aid | C27: aid-first | D27: Read the burns guide and mark confusing words | E27: User | F27: S | G27: 10 | H27: $ | I27: Open | J27: Online | L27: 1 | M27: Good for you if you have never studied first aid | N27: The guide is for ordinary people. If you stumble on a word, so will a scared parent. | O27: 1. Read the master burns guide 2. Underline any word you would not use 3. Say what you would do after reading it | P27: Marked-up guide | Q27: Every hard word marked | R27: 1 nurse Checker | S27: Collects marks from all readers | T27: Reads honestly | U27: Phone | V27: none | W27: a6
A28: a8 | B28: aid | C28: aid-first | D28: Build the 30-word Hausa first-aid glossary | E28: Expert | F28: M | G28: 60 | H28: $ | I28: Locked | J28: Online | L28: 2 | M28: Good for you if you speak Hausa | N28: Words like 'airway' and 'unconscious' must be the same in all 20 guides. | O28: 1. Take the 30-term list 2. Give the common Hausa word or phrase 3. Note if a picture is better 4. Agree with a second speaker | P28: Glossary in Weblate | Q28: All 30 terms agreed by 2 speakers | R28: 1 Hausa Checker | S28: Proposes candidates from public dictionaries | T28: Chooses what people really say | U28: Weblate glossary | V28: Native Hausa | W28: a15, a16 | X28: A term has a formal and a street word. Which? | Y28: Street word | Formal word | Both, street first
A29: a9 | B29: aid | C29: aid-first | D29: Fix agent drafts of all 20 guides in Amharic | E29: Expert | F29: L | G29: 250 | H29: $ | I29: Locked | J29: Online | L29: 2 | M29: Good for you if you speak Amharic | N29: A full language set. Usually a day of careful work. | O29: 1. Load the Amharic glossary 2. Fix each of 20 drafts 3. Check the Ge'ez script renders on a phone 4. Log hard lines | P29: 20 fixed guides in Weblate | Q29: All 20 marked translated; glossary terms used | R29: Stage 3 checker | S29: Drafts and flags uncertain lines | T29: Fixes meaning | U29: Weblate, Noto Sans Ethiopic | V29: Native Amharic | W29: a8
A30: a10 | B30: aid | C30: aid-first | D30: Check the 20 Yoruba guides line by line | E30: Checker | F30: M | G30: 100 | H30: $ | I30: Locked | J30: Online | L30: 3 | M30: Good for you if you speak Yoruba | N30: An independent native speaker is the last line before the public. | O30: 1. Confirm you did not translate this set 2. Compare each guide to the master 3. Mark any meaning change 4. Send safety issues to a nurse | P30: 20 guides marked checked + issue list | Q30: All 20 approved or returned with reasons | R30: Nurse samples 2 guides | S30: Highlights lines that differ most from the master | T30: Judges each line | U30: Weblate review | V30: Native Yoruba | W30: a9
A31: a11 | B31: aid | C31: aid-first | D31: Back-translate 10% of guides and compare | E31: Checker | F31: M | G31: 80 | H31: $ | I31: Locked | J31: Online | L31: 3 | M31: Good for you if you read medical English carefully | N31: Back-translation catches errors a single checker may miss. | O31: 1. Draw 100 random pairs 2. Get each back-translated to English by a different speaker 3. Compare to master 4. Flag safety-changing differences | P31: Comparison sheet for 100 pairs | Q31: Zero safety-changing errors left open | R31: Lead nurse | S31: Draws the random sample and lines up texts | T31: Judges what counts as safety-changing | U31: Spreadsheet, Weblate export | V31: Medical English | W31: a10 | X31: Back-translation shows 2 safety errors in one language. What now? | Y31: Re-check that whole language | Fix only flagged lines
A32: a12 | B32: aid | C32: aid-first | D32: Build the offline app under 30 MB | E32: Maker | F32: L | G32: 300 | H32: $ | I32: Locked | J32: Online | L32: 4 | M32: Good for you if you can build Android apps | N32: Many readers have cheap phones and little data. | O32: 1. Bundle text and SVGs 2. Add local emergency numbers by country 3. Test on a 2 GB Android phone 4. Publish the open-source code | P32: APK + repo link | Q32: Opens offline in all 50 languages on a 2 GB phone | R32: 3 Checkers on different phones | S32: Writes and tests build scripts | T32: Tests on a real phone | U32: Android SDK, Noto fonts | V32: Mobile development | W32: a11
A33: a13 | B33: aid | C33: aid-first | D33: Lay out printable A5 cards for all languages | E33: Maker | F33: M | G33: 80 | H33: $ | I33: Locked | J33: Online | L33: 4 | M33: Good for you if you can do print layout | N33: Cards go on clinic and classroom walls. | O33: 1. Build one template 2. Auto-fill each language 3. Check right-to-left and long scripts fit 4. Export PDFs | P33: 1,000 PDFs in a zip | Q33: Random 20 print correctly | R33: 2 Checkers print and inspect | S33: Fills templates | T33: Checks layouts | U33: Typst or Scribus | V33: Layout | W33: a11, a4
A34: m1 | B34: llm | C34: llm-data | D34: Clean 10,000 lines of Odia text | E34: Expert | F34: S | G34: 500 | H34: ₹ | I34: Open | J34: Online | L34: 1 | M34: Good for you if you read Odia | N34: Odia is one of the languages below the 5-million-word floor. Much of the Odia text online uses old non-Unicode fonts or mixes in English menus and ads. Clean lines decide whether the model ever learns Odia properly. | O34: 1. Open the batch of 10,000 lines your agent pre-sorted 2. Fix or drop lines with broken characters from legacy fonts 3. Drop menus, ads, and lines that are not Odia 4. Mark any line with names, phone numbers or addresses 5. Submit the clean file with a one-line note on what you dropped | P34: A UTF-8 text file of clean Odia lines plus a dropped-lines log (counts by reason) | Q34: At most 5% of a 200-line random sample is junk, non-Odia or contains personal data | R34: 1 Odia-reading Checker reviews 200 random lines | S34: Runs language-ID and script checks, flags legacy-font garbage, strips obvious phone and ID numbers, and pre-sorts the lines into keep, maybe and drop | T34: Reads the 'maybe' lines, judges what is real Odia, and fixes text the scripts cannot | U34: IndicLID, IndicNLP Library normaliser, the shared cleaning sheet | V34: Reads and writes Odia fluently | W34: m9 | X34: About 15% of lines mix Odia with English words in Latin script (code-mixing). Keep or drop? | Y34: Keep: this is how people really write | Drop: keep the corpus pure Odia | Keep, but cap mixed lines at 10% of the batch
A35: m2 | B35: llm | C35: llm-data | D35: Write 50 test questions in Kannada | E35: Expert | F35: S | G35: 600 | H35: ₹ | I35: Open | J35: Online | L35: 1 | M35: Good for you if you speak Kannada and like writing puzzles | N35: We test the model on questions written by native speakers, not translated from English. They are written now and locked away before training, so the model can never have seen them. | O35: 1. Write 50 questions across reading, grammar, local knowledge and everyday tasks 2. Write the correct answer and a short scoring note for each 3. Avoid anything copied from a website or textbook 4. Submit through the frozen-test form so the file is hashed | P35: 50 question/answer/scoring-note rows in the test template, with the SHA-256 hash recorded | Q35: A second Kannada speaker agrees with at least 45 of 50 answers. A web search finds no copied questions. | R35: 1 Kannada-speaking Checker answers all 50 blind and compares | S35: Checks for duplicates against public benchmarks, searches the web for copied text, and formats and hashes the file | T35: Writes the questions in natural Kannada with local context only a speaker knows | U35: Frozen-test form, web search | V35: Native Kannada; some teaching or writing experience helps
A36: m3 | B36: llm | C36: llm-data | D36: Check 100 model answers in Hindi | E36: Checker | F36: S | G36: 500 | H36: ₹ | I36: Open | J36: Online | L36: 1 | M36: Good for you if you read Hindi closely | N36: Bharat Base trained a 100-million-parameter pilot model. Grading its Hindi answers tests our scoring guide before the real evaluation, when it matters most. | O36: 1. Read each question and the pilot model's answer 2. Score 0–2 for correctness and 0–2 for natural Hindi 3. Flag any answer where the guide was unclear 4. Submit the scores and the list of unclear rules | P36: Score sheet of 100 rows plus a list of scoring-guide problems | Q36: A second grader's scores agree on at least 80% of items | R36: A second Hindi Checker re-grades 25 at random | S36: Lays out each question and answer side by side, records scores, and computes agreement | T36: Judges whether the Hindi is correct and natural, which only a fluent reader can do | U36: Grading sheet, scoring guide v0.3 | V36: Fluent Hindi reader
A37: llm-base-back | B37: llm | C37: llm-base | D37: Back Bharat Base's GPU bill | E37: Patron | F37: S | G37: 0 | H37: ₹ | I37: Open | J37: Online | L37: 1 | M37: Good for you if you want to fund open AI for Indian languages | N37: Bharat Base has about 3 weeks of GPU money left for test runs and is ₹14 lakh short of the full training plan. Backing them is the play. Unspent money goes back if the mission stops. | O37: 1. Read the squad's GPU budget and burn rate 2. Choose an amount 3. Confirm the backing | P37: Backing receipt | Q37: Payment confirmed | R37: Automatic ledger check | S37: Summarises the squad's spend so far and what each ₹10,000 buys (about 40 GPU-hours) | T37: Decides whether and how much to back | U37: Joystick wallet | V37: none
A38: m15 | B38: llm | C38: llm-base | D38: Decide which languages get extra repeats | E38: Leader | F38: M | G38: 1500 | H38: ₹ | I38: Open | J38: Online | L38: 1 | M38: Good for you if you can make a firm call and own it | N38: Some small languages will stay below the floor. The Leader must decide how many times to repeat their text, which helps them but risks the model memorising it, and say so publicly before the corpus is frozen. | O38: 1. Read the per-language word counts after dedup (m8) 2. Read the pilot-model loss for each language 3. Set a repeat count (1–4) per language 4. Publish the table with one line of reasoning per language | P38: A 22-row language-mix table with repeat counts and reasons | Q38: Mission creator and 2 Checkers approve the table; no language is repeated more than 4 times | R38: 2 Checkers compare the table against the dedup report | S38: Builds the counts table and simulates the token totals for each mix | T38: Makes the trade-off between fairness to small languages and model quality | U38: Dedup report, pilot-model losses | V38: LLM training judgement | W38: m8 | X38: Santali has 3 million clean words, below the 5-million floor | Y38: Repeat 4× and flag it in the model card | Pause the freeze 3 weeks for more m10 sentences | Ship without Santali and say so
A39: m4 | B39: llm | C39: llm-base | D39: Set up the training run on 64 GPUs | E39: Maker | F39: L | G39: 8000 | H39: ₹ | I39: Locked | J39: Online | L39: 2 | M39: Good for you if you have run multi-GPU training | N39: The main run must survive crashes and node failures without losing days. A good setup saves more GPU money than any other single task. | O39: 1. Set up data loading from the frozen corpus with the chosen language mix 2. Set checkpoints every 2 hours to shared storage 3. Run a 1-hour smoke test on all 64 GPUs and measure throughput 4. Add alerts for loss spikes and dead nodes 5. Write the restart runbook | P39: Training config repo, smoke-test log with tokens per second per GPU, and the restart runbook | Q39: The smoke test reaches at least 35% of peak GPU throughput, and a forced restart from checkpoint resumes in 15 minutes or less | R39: 2 Checkers (ML) kill one node on purpose and watch it recover | S39: Writes config files, launches the smoke test, and parses throughput logs | T39: Chooses parallelism settings, judges whether throughput is good enough, and owns the go/no-go | U39: 64-GPU cluster, PyTorch training stack, shared storage | V39: Distributed training | W39: m7, m11, llm-base-back
A40: m5 | B40: llm | C40: llm-tune | D40: Plan how Fine-Tune Force joins Bharat Base | E40: Planner | F40: M | G40: 1500 | H40: ₹ | I40: Open | J40: Online | L40: 1 | M40: Good for you if you like getting two teams to agree | N40: Both squads use the same data, so running them apart doubles the cost. The merge has to keep what Fine-Tune Force does well: starting from a stronger model. | O40: 1. List both squads' people, money, code and test results 2. Propose one plan with a from-scratch arm and a tuned arm 3. Agree how the ₹2 lakh Fine-Tune Force raised moves over 4. Get both Leaders to sign | P40: A 1-page merge plan signed by both Leaders | Q40: Both Leaders and the mission creator approve the plan in writing | R40: Mission creator + 1 Checker | S40: Drafts the plan from both squads' boards and compares costs | T40: Negotiates who leads what and how credit is shared | U40: Squad boards, budget sheet | V40: Planning, negotiation | W40: m7 | X40: Does the tuned arm survive the merge? | Y40: Keep both arms; pick the winner in Stage 3 | Drop the tuned arm to save GPUs | Make the tuned arm the main plan
A41: m6 | B41: llm | C41: llm-data | D41: Find 5 free sources of Tamil text | E41: Expert | F41: S | G41: 400 | H41: ₹ | I41: Done | J41: Online | L41: 1 | M41: Good for you if you read Tamil | N41: Tamil has plenty of text, but much of it has unclear licences. We need sources we can prove we are allowed to use. | O41: 1. Search for public-domain, government and openly licensed Tamil text 2. Record the licence and URL of each 3. Estimate the word count of each | P41: 5 rows in the licence log with URL, licence and word estimate | Q41: Each licence is confirmed from the source's own page | R41: 1 Checker opens all 5 and confirms the licence | S41: Searches, reads licence pages and estimates size | T41: Judges whether the text is real, good Tamil and worth the effort | U41: Web search, licence log | V41: Reads Tamil
A42: m7 | B42: llm | C42: llm-base | D42: Build and test one tokenizer for 12 scripts | E42: Maker | F42: L | G42: 6000 | H42: ₹ | I42: Open | J42: Online | L42: 1 | M42: Good for you if you can read Python and like scripts and alphabets | N42: The tokenizer decides how many pieces each word is cut into. If Odia words become 8 pieces and English words 1.3, the model is slower and worse at Odia. It cannot change after training starts. | O42: 1. Sample balanced text from all 22 languages (cap Hindi so it does not dominate) 2. Train SentencePiece candidates at 3 vocabulary sizes 3. Measure tokens per word for each language on FLORES-200 sentences 4. Check rare scripts (Ol Chiki, Meitei Mayek) are not split into single letters 5. Publish the comparison table | P42: Tokenizer files, a per-language tokens-per-word table, and a recommendation | Q42: Every language is at or below 1.5× English tokens per word, or the table shows why not | R42: 2 Checkers re-run the measurement on 3 languages | S42: Builds the samples, trains the candidates and computes the tables | T42: Picks the vocabulary size and checks by eye that the splits make sense to a reader | U42: SentencePiece, FLORES-200, IndicNLP normaliser | V42: Tokenizers, Python | W42: m6 | X42: Which vocabulary size? | Y42: 32k: small embeddings, rare scripts split more | 64k: balance | 128k: best splits, but eats a big part of a 1B model
A43: m8 | B43: llm | C43: llm-data | D43: Remove duplicates and test leaks from the corpus | E43: Maker | F43: M | G43: 1800 | H43: ₹ | I43: Open | J43: Online | L43: 1 | M43: Good for you if you like data pipelines | N43: Web text repeats the same news story thousands of times, and test questions can sneak in. Both make the model look better than it is. | O43: 1. Run exact and near-duplicate removal per language 2. Search the corpus for every frozen test question 3. Remove matches and log counts 4. Report the words remaining per language | P43: Dedup report: words before and after per language, and test-leak hits removed | Q43: Zero frozen test items are found in the corpus at 13-word overlap | R43: 1 Checker plants 20 test sentences and confirms all 20 are caught | S43: Runs MinHash dedup and n-gram leak search and writes the report | T43: Sets the similarity threshold and spot-checks what was removed | U43: MinHash-LSH, frozen test hashes | V43: Data engineering | W43: m2
A44: m9 | B44: llm | C44: llm-data | D44: Log licences for the first 40 text sources | E44: Checker | F44: M | G44: 1200 | H44: ₹ | I44: Done | J44: Online | L44: 1 | M44: Good for you if you read terms pages carefully | N44: An open model is only open if we have the right to its text. One bad source can force a re-train. | O44: 1. Open each source's terms page 2. Classify it: public domain, Sec. 52 government work, CC licence, or unclear 3. Drop the unclear ones 4. Record the evidence link | P44: 40 rows in the licence log, each with an evidence link | Q44: Every row has a licence class and a working evidence link | R44: Mission creator spot-checks 8 rows | S44: Fetches terms pages and drafts a classification | T44: Makes the final call on unclear cases | U44: Licence log, Copyright Act 1957 Sec. 52 | V44: Careful reading; basic copyright knowledge
A45: m10 | B45: llm | C45: llm-data | D45: Type 200 sentences in your mother tongue | E45: User | F45: S | G45: 300 | H45: ₹ | I45: Open | J45: Online | L45: 1 | M45: Good for you if your mother tongue is Bodo, Dogri, Santali, Kashmiri or another small language | N45: For Bodo, Dogri, Santali and Kashmiri there is too little open text. Everyday sentences from real speakers, given freely under CC-BY, close part of the gap. | O45: 1. Pick a topic list (market, weather, school, farming) 2. Type 200 sentences in your own words 3. Do not include real names, phone numbers or private details 4. Agree to the CC-BY licence | P45: 200 sentences in the submission form with the licence ticked | Q45: Language-ID confirms the language for 95% or more of sentences and a speaker finds them natural | R45: 1 Checker who speaks the language reads 40 | S45: Suggests topics, checks the script and language, and flags personal details | T45: Writes natural sentences only a native speaker can | U45: Submission form with a script keyboard | V45: none
A46: m11 | B46: llm | C46: llm-base | D46: Choose final model size and token budget | E46: Leader | F46: M | G46: 1500 | H46: ₹ | I46: Locked | J46: Online | L46: 2 | M46: Good for you if you can weigh cost against quality | N46: The size of the model decides the GPU bill, whether it fits a laptop, and how many times we must repeat rare-language text. This is the most expensive single decision in the mission. | O46: 1. Read the test-run results at 100M and 400M parameters 2. Estimate GPU-hours for 1B and 2B at the available tokens 3. Check against money raised 4. Decide and publish the reasons | P46: A 1-page decision note with GPU-hour and cost estimates | Q46: Mission creator and 2 Checkers agree that the estimate matches the budget, with at least 15% to spare | R46: 2 Checkers (ML) re-do the compute arithmetic | S46: Fits scaling curves from the test runs and prices the options | T46: Weighs laptop speed against quality and makes the call | U46: Test-run logs, budget sheet | V46: LLM training economics | W46: m7, m15 | X46: With about 35 billion tokens of text, which model? | Y46: 1B, 4 epochs: fast on laptops, cheaper | 2B, 4 epochs: better quality, slower on laptops | 2B with a lower ₹ cap: fewer test runs
A47: m12 | B47: llm | C47: llm-data | D47: Score the model in all 22 languages | E47: Checker | F47: L | G47: 5000 | H47: ₹ | I47: Locked | J47: Online | L47: 3 | M47: Good for you if you know evaluation and basic statistics | N47: This is the result the mission is judged on. Every language gets a score with a confidence range, and losses are published too. | O47: 1. Run open benchmarks and frozen native tests on our model 2. Run the same tests on 2 open models of the same size 3. Collect human grades for open-ended answers 4. Build one table with confidence ranges 5. Mark wins only where the gap is larger than the range | P47: A 22-row results table, scoring scripts and raw outputs | Q47: Re-running 10% of the items gives the same scores within 1 point | R47: 2 Checkers re-run scripts; 1 native Expert per language audits 20 human grades | S47: Runs the evaluation harness, collects outputs and computes confidence ranges | T47: Decides what counts as a fair comparison and signs the table | U47: lm-evaluation-harness, IN22, FLORES-200, frozen tests | V47: Evaluation, statistics | W47: m4, m2, m3 | X47: The test set for Dogri has only 200 items and the model wins by 1.5 points, inside the margin of error | Y47: Count it as a tie | Write 300 more items and re-test | Count it as a win with a footnote
A48: m13 | B48: llm | C48: llm-tune | D48: Shrink the model to run on an 8 GB laptop | E48: Maker | F48: L | G48: 6000 | H48: ₹ | I48: Locked | J48: Online | L48: 4 | M48: Good for you if you have quantised models before | N48: Most of our users have a cheap laptop and no GPU. A 4-bit build must keep most of its quality in every language, not just Hindi. | O48: 1. Build 4-bit and 5-bit GGUF versions 2. Re-run the 22-language test on each 3. Time it on 3 laptops with 8 GB RAM and no GPU 4. Publish the quality loss per language | P48: GGUF files, a speed table and a per-language quality-loss table | Q48: 10 or more tokens per second on all 3 laptops, and no language loses more than 3 points | R48: 2 Checkers install it on their own laptops and time it | S48: Runs quantisation and the test suite and builds the tables | T48: Tests on real laptops and judges whether the output still reads naturally | U48: llama.cpp, GGUF, 3 test laptops | V48: Model quantisation | W48: m12
A49: m16 | B49: llm | C49: llm-data | D49: Recruit Bodo and Santali speakers with a short video | E49: Storyteller | F49: S | G49: 500 | H49: ₹ | I49: Open | J49: Online | L49: 1 | M49: Good for you if you can make a short video that people share | N49: The quest m10 only works if speakers of small languages hear about it. A 60-second video in Bodo or Santali, made with a speaker, reaches people a poster in English never will. | O49: 1. Pair with a Bodo or Santali speaker from the squad 2. Script 60 seconds: what the model is, why their language matters, how to join m10 3. Record it with subtitles in the language and in English 4. Post the link with a tracking code | P49: A video file or link, plus a tracking code | Q49: The video is approved by the speaker and brings in 20 or more m10 sign-ups in 3 weeks | R49: 1 Checker who speaks the language confirms the content; sign-ups counted automatically | S49: Drafts the script, makes subtitles and counts sign-ups | T49: Works with the speaker so the message sounds right to that community | U49: Phone camera, subtitle editor | V49: Short video, community outreach | W49: m10
A50: h6 | B50: harness | C50: har-loop | D50: Build the quest loop: pick, do, hand in | E50: Maker | F50: L | G50: 400 | H50: $ | I50: Done | J50: Online | L50: 1 | M50: Good for you if you write TypeScript | N50: The core of the engine: the agent reads a quest, plans, calls tools, checks its own output and hands in. Everything else plugs into this loop. | O50: 1. Write the plan → act → observe loop with a turn cap 2. Add token and time caps that stop the run cleanly 3. Log every model call and tool call with a run ID 4. Hand in through the quest API | P50: Merged PR with tests and a sample run log | Q50: 16 of 20 replay quests pass and no run exceeds its caps | R50: 2 Checkers replay 5 runs each | S50: Writes most of the code and tests | T50: Designs the loop and the stop conditions and reviews every line that touches caps | U50: TypeScript, Node.js, model API | V50: TypeScript, agent design | W50: h7
A51: h7 | B51: harness | C51: har-crew | D51: Record 20 real quests as a replay test set | E51: Planner | F51: M | G51: 80 | H51: $ | I51: Done | J51: Online | L51: 1 | M51: Good for you if you like designing tests | N51: Agents are noisy, so we need the same 20 quests to run again and again. Recorded tool responses make runs repeatable and free of side effects. | O51: 1. Pick 20 finished quests across 5 missions 2. Record every tool response they needed 3. Write a pass/fail test for each 4. Store them as fixtures | P51: 20 replay fixtures with pass/fail tests | Q51: Each fixture replays with no network access | R51: 1 Checker runs all 20 offline | S51: Captures tool responses and drafts the tests | T51: Chooses quests that cover the hard cases, not just the easy ones | U51: Replay recorder, quest archive | V51: Testing
A52: h3 | B52: harness | C52: har-crew | D52: Write the rules for when an agent must ask its human | E52: Planner | F52: S | G52: 30 | H52: $ | I52: Open | J52: Online | L52: 2 | M52: Good for you if you think like a careful user | N52: If the agent asks too often, players give up. If it asks too rarely, it pays or pushes without consent. These rules become the 'ask' level in every tool manifest. | O52: 1. List every action the 10 tools can take 2. Mark each one allow, ask or deny 3. Write one plain sentence per 'ask' that the player will see 4. Get 3 players to read it and say what they'd expect | P52: An action table (allow/ask/deny) plus prompt texts | Q52: Every write, spend and outbound send is 'ask' or 'deny' unless capped | R52: 2 Checkers try to find an action missing from the table | S52: Pulls the list of actions from the tool code and drafts the table | T52: Judges what a normal player would want to be asked about | U52: Tool source, table template | V52: Product judgement | W52: h6 | X52: Opening a pull request on the player's own repo: allow or ask? | Y52: Allow: it's reversible | Ask: it's public | Allow on branches, ask on main
A53: h8 | B53: harness | C53: har-loop | D53: Approve the permission model for all tools | E53: Leader | F53: M | G53: 80 | H53: $ | I53: Open | J53: Online | L53: 2 | M53: Good for you if you can make a firm design call | N53: Every tool needs the same shape of manifest so the engine can enforce it in one place. Once Makers build to it, changing it is expensive. | O53: 1. Read the Planner's allow/ask/deny table 2. Pick the manifest fields: reads, writes, spends, network hosts, secrets 3. Decide how tool output is marked as untrusted 4. Publish v1 and freeze it for 4 weeks | P53: Manifest spec v1 with an example for GitHub and the browser | Q53: Both squads' Leads sign it, and the GitHub example passes the spec validator | R53: 2 Checkers review it against OWASP LLM06 (Excessive Agency) | S53: Drafts the spec and a validator from the table | T53: Makes the trade-off between safety and how often players are interrupted | U53: MCP tool schema, h3 table | V53: System design, security basics | W53: h3 | X53: What happens when a tool tries an action its manifest doesn't list? | Y53: Hard deny and log | Pause and ask the human | Deny, but let the human add it to the manifest
A54: h1 | B54: harness | C54: har-loop | D54: Add a GitHub tool the agent can use safely | E54: Maker | F54: M | G54: 100 | H54: $ | I54: Open | J54: Online | L54: 2 | M54: Good for you if you know the GitHub API | N54: Most quests touch code. The tool must let the agent read issues and open PRs without letting it merge, delete or touch other repos. | O54: 1. Use a GitHub App with fine-grained, per-repo permissions 2. Write the manifest: read issues, write branches, open PRs; no merge, no delete 3. Mark issue and comment text as untrusted 4. Add tests for every denied action | P54: Merged PR with manifest, tests and a demo run log | Q54: All denied-action tests pass, and the red-team suite's 10 GitHub attacks fail | R54: 2 Checkers run the red-team suite on it | S54: Writes the wrapper code and tests | T54: Sets the GitHub App permissions and reviews the manifest line by line | U54: GitHub Apps, test org, manifest spec v1 | V54: TypeScript, GitHub API | W54: h8
A55: h15 | B55: harness | C55: har-loop | D55: Make the browser tool check before it clicks | E55: Maker | F55: M | G55: 90 | H55: $ | I55: Open | J55: Online | L55: 2 | M55: Good for you if you have written Playwright or Selenium tests | N55: Loop Lab's blocker: when a page shifts, the browser tool clicks the wrong button. On a payment page that is dangerous. | O55: 1. Before a click, re-read the target's text and role from the page 2. Refuse if it doesn't match what the agent asked for 3. After the click, confirm the page changed as expected 4. Add 20 shifting-layout test pages | P55: PR plus a before/after wrong-click rate on 20 test pages | Q55: Wrong clicks fall to 0 of 200 test clicks | R55: 1 Checker adds 5 new shifting pages the Maker hasn't seen | S55: Builds the test pages and runs the click trials | T55: Decides what counts as a match and reviews the failure cases | U55: Playwright, test pages | V55: Browser automation | W55: h8
A56: h10 | B56: harness | C56: har-loop | D56: Add spend caps with hold-then-pay | E56: Maker | F56: M | G56: 120 | H56: $ | I56: Open | J56: Online | K56: Test-mode wallets only. | L56: 2 | M56: Good for you if you've built anything that moves money | N56: The agent must never spend more than the quest allows, even if a network retry or a confused plan asks twice. | O56: 1. Every spend first places a hold against the quest's cap 2. Pay only with an idempotency key tied to the hold 3. Write each step to an append-only double-entry ledger with a trace ID 4. Release unused holds when the quest ends | P56: PR with ledger schema, tests and a retry-storm test | Q56: In 1,000 simulated retries, zero payments are made twice and no quest exceeds its cap | R56: 2 Checkers run the retry-storm test and reconcile the ledger | S56: Writes the code and the simulation | T56: Designs the ledger and reviews every line that moves money | U56: Payment sandbox, Postgres | V56: Payments, databases | W56: h8 | X56: A quest needs $12 more than its cap to finish | Y56: Hard stop: hand in partial work | Ask the human to raise the cap | Auto-allow up to 10% over
A57: h11 | B57: harness | C57: har-crew | D57: Run every tool call in a throwaway sandbox | E57: Maker | F57: L | G57: 300 | H57: $ | I57: Open | J57: Online | L57: 2 | M57: Good for you if you know Linux and containers | N57: If a fooled agent runs a bad command, the damage should stop at a sandbox that is thrown away after the call. | O57: 1. Start a microVM per quest with no network by default 2. Allow only the hosts listed in the tool's manifest through a proxy 3. Mount secrets only for the tool that needs them, then wipe them 4. Measure start-up time | P57: PR, start-up timing table, and an escape-attempt test log | Q57: Sandbox starts in under 1 second; 20 escape attempts all fail | R57: 1 security Expert and 1 Checker try 5 escapes each | S57: Writes the sandbox config and test scripts | T57: Reviews network and secret rules, which are the parts that matter | U57: Firecracker or gVisor, egress proxy | V57: Linux, containers | W57: h8
A58: h9 | B58: harness | C58: har-crew | D58: Write 30 prompt-injection attacks for the tools | E58: Expert | F58: M | G58: 100 | H58: $ | I58: Open | J58: Online | K58: Attack only the test sandbox; never real sites or accounts. | L58: 2 | M58: Good for you if you enjoy breaking things | N58: Web pages, issues and files can carry hidden instructions. Each attack you write becomes a permanent test in CI. | O58: 1. Write 10 attacks in web pages (hidden text, alt text, fake system messages) 2. Write 10 in GitHub issues and comments 3. Write 10 in files the agent reads 4. For each, state what a successful attack would do (leak, spend, write) 5. Run them and record which succeed | P58: 30 attack fixtures with expected-safe outcomes and a results table | Q58: All 30 are in the CI suite; every success has an issue filed | R58: 2 Checkers re-run 10 at random | S58: Generates variations of each attack and runs the suite | T58: Invents attacks that are actually new, not just reworded | U58: Red-team suite, test sandbox, OWASP LLM01 | V58: Security mindset | W58: h11 | X58: An attack in a web page makes the agent try to open an unlisted host. The sandbox blocks it, but the agent tried. Pass or fail? | Y58: Pass: the sandbox did its job | Fail: the agent was fooled; fix the prompt too | Pass, but log it as a near miss
A59: h2 | B59: harness | C59: har-loop | D59: Try to make the agent spend money it shouldn't | E59: Checker | F59: S | G59: 40 | H59: $ | I59: Open | J59: Online | K59: Test accounts only. | L59: 2 | M59: Good for you if you like finding loopholes | N59: The spend caps are only as good as the attacks they survive. You are paid to find a way around them. | O59: 1. Read the spend cap design 2. Try 10 ways to spend over the cap (retries, split payments, injected instructions) 3. Record each attempt and result 4. File an issue for anything that gets through | P59: Attempt log with 10 rows and any issues filed | Q59: 10 distinct attempts are logged; each success is reproducible | R59: 1 Checker reproduces any reported success | S59: Scripts the attempts and records results | T59: Thinks up attacks the designers didn't | U59: Test-mode wallet, ledger viewer | V59: Curiosity; some coding helps | W59: h10
A60: h4 | B60: harness | C60: har-loop | D60: Run the engine on a real quest and log what broke | E60: User | F60: S | G60: 20 | H60: $ | I60: Open | J60: Online | L60: 2 | M60: Good for you if you have 15 minutes and an agent | N60: Tests miss what real players hit. Run your agent on a real S quest from any mission and tell us every moment it confused, stalled or surprised you. | O60: 1. Install the engine 2. Pick an Open S quest 3. Let your agent run it, approving or refusing as asked 4. Note each confusing prompt, stall or wrong click | P60: A short report with the trace ID and a list of problems | Q60: The report includes a trace ID that replays | R60: 1 Checker replays the trace | S60: Runs the quest and exports the trace | T60: Notices what feels wrong or unsafe | U60: The engine, any Open S quest | V60: none | W60: h1
A61: h5 | B61: harness | C61: har-crew | D61: Explain the engine in a 2-minute video | E61: Storyteller | F61: S | G61: 25 | H61: $ | I61: Open | J61: Online | L61: 2 | M61: Good for you if you can explain tech to a friend | N61: Builders join when they get the safety model in 2 minutes: manifests, sandboxes, caps and checks. | O61: 1. Read the manifest spec and the sandbox design 2. Script: one quest, four safety layers, one attack that fails 3. Record a screen capture with voice 4. Add the contributor link | P61: Video link plus a script | Q61: Kit or Lena confirm it is accurate, and it is under 2:15 | R61: 1 Checker watches it for technical errors | S61: Drafts the script and captions | T61: Makes it clear and human | U61: Screen recorder | V61: Explaining tech simply | W61: h8
A62: har-crew-back | B62: harness | C62: har-crew | D62: Back Small Crew's model bill | E62: Patron | F62: S | G62: 0 | H62: $ | I62: Open | J62: Online | L62: 2 | M62: Good for you if you want safe agents to exist | N62: Small Crew runs 30 agents, and red-team runs multiply the model bill. They are $5,500 short. Backing them is the play. | O62: 1. Read the squad's cost per red-team run 2. Choose an amount 3. Confirm | P62: Backing receipt | Q62: Payment confirmed | R62: Automatic ledger check | S62: Shows what each $100 buys (about 25 full red-team runs) | T62: Decides whether to back | U62: Joystick wallet | V62: none
A63: h12 | B63: harness | C63: har-crew | D63: Build the checker agent that reviews before humans | E63: Maker | F63: L | G63: 350 | H63: $ | I63: Locked | J63: Online | L63: 3 | M63: Good for you if you have built LLM evals | N63: The checker agent sees only the quest, the result and the evidence, never the maker's reasoning. It writes notes for the human reviewer. | O63: 1. Give it a separate prompt and, where possible, a different model 2. Feed it result plus evidence only 3. Output: pass, fail or unsure, with reasons 4. Never let it approve a payment | P63: PR, rubric, and its scores on the replay set | Q63: It flags at least 45 of 50 planted bad results | R63: 3 human Checkers review 30 of its decisions | S63: Builds and tunes the checker | T63: Writes the rubric and judges the hard cases | U63: Replay set, planted bad results | V63: Agent design, evals | W63: h7, h9, h13 | X63: Should the checker use the same model as the maker? | Y63: Same model, different prompt: cheaper | Different model: fewer shared blind spots | Both, and flag disagreements
A64: h13 | B64: harness | C64: har-loop | D64: Plant 50 bad results to test the checker | E64: Expert | F64: M | G64: 100 | H64: $ | I64: Locked | J64: Online | L64: 3 | M64: Good for you if you're good at spotting subtle mistakes | N64: A checker is only measured by what it misses. Planted bad results (subtly wrong code, fake photos, wrong totals) give a fixed test. | O64: 1. Write 50 results that look done but are wrong 2. Cover 5 kinds of error 3. Write why each is wrong 4. Keep them hidden from the Maker | P64: 50 planted results with answer keys | Q64: 2 human Checkers find each error with the answer key | R64: 2 Checkers | S64: Helps produce variations | T64: Designs errors that a quick look would miss | U64: Quest archive | V64: Domain knowledge in at least one mission | W64: h7
A65: h14 | B65: harness | C65: har-loop | D65: Load-test 1,000 agents against the ledger | E65: Maker | F65: L | G65: 400 | H65: $ | I65: Locked | J65: Online | K65: Test-mode wallets only. | L65: 4 | M65: Good for you if you've run load tests | N65: Money bugs hide in races and retries. 72 hours with 1,000 agents and injected outages is how they come out. | O65: 1. Launch 1,000 sandboxed agents on replay quests 2. Inject network drops and payment timeouts 3. Reconcile the ledger with the sandbox every hour 4. Trace cost per quest with OpenTelemetry 5. Report every mismatch | P65: Load-test report, reconciliation logs and dashboards | Q65: Zero mismatches, zero double payments, and every spend alert fires within 60 seconds | R65: 2 Checkers reconcile 100 transactions by hand | S65: Runs the fleet and the reconciliation | T65: Designs the failures and calls stop if money looks wrong | U65: Sandbox fleet, payment sandbox, OpenTelemetry | V65: Distributed systems | W65: h10, h12 | X65: On hour 40 one ledger entry is off by $0.01 | Y65: Halt all agents and investigate | Keep running, freeze that wallet | Restart the 72 hours after the fix
A66: r5 | B66: reef | C66: reef-sky | D66: Label 200 satellite photos | E66: Expert | F66: S | G66: 20 | H66: $ | I66: Done | J66: Online | L66: 1 | M66: Good for you if you've snorkelled or know reefs from above | N66: Part of the 1,000-tile pilot. Each tile is marked as coral, sand, rubble, algae or deep water. | O66: 1. Open the labelling tool 2. Mark the cover class for each tile 3. Flag tiles that are too cloudy or deep to call | P66: 200 labelled tiles | Q66: At least 85% agreement with a Checker's re-label of 20 | R66: 1 Checker re-labels 20 | S66: Pre-labels tiles and flags cloud | T66: Makes the call on tiles the agent isn't sure about | U66: Labelling tool, Sentinel-2 tiles | V66: Some reef or map experience
A67: r6 | B67: reef | C67: reef-ops | D67: Pick 200 survey sites near Cebu, Bohol and Fiji | E67: Planner | F67: M | G67: 80 | H67: $ | I67: Done | J67: Online | L67: 1 | M67: Good for you if you know the Visayas or Fiji coast | N67: Sites must cover healthy and damaged reefs, different depths, and places a boat can reach. | O67: 1. Overlay labelled tiles with reef extent and heat stress 2. Pick sites across classes and depths 3. Check boat access and protected-area permits 4. Hold back 40 sites for testing | P67: Site list with GPS, class, depth and the 40 held-back sites marked | Q67: Each class has at least 40 sites, and the held-back set is locked | R67: Mission creator + 1 Checker | S67: Runs the overlays and drafts the list | T67: Uses local knowledge of which sites are reachable and safe | U67: QGIS, Allen Coral Atlas, Coral Reef Watch | V67: Survey planning | W67: r5
A68: r11 | B68: reef | C68: reef-ops | D68: Write a scoring guide anyone can follow | E68: Expert | F68: M | G68: 100 | H68: $ | I68: Done | J68: Online | L68: 2 | M68: Good for you if you've done reef surveys | N68: Different divers scored the same site differently. One guide with example photos makes scores comparable. | O68: 1. Define the 3 classes with 5 photo examples each 2. Write the transect and quadrat method 3. Write the snorkel version for reef flats 4. Test it with 2 divers on the same site | P68: Guide PDF with example photos | Q68: 2 divers scoring the same site agree within 10% cover | R68: 1 marine-biology Checker | S68: Lays out the guide and collects example photos | T68: Writes the scoring method from experience | U68: Coral Health Chart, CoralNet | V68: Reef surveys
A69: r7 | B69: reef | C69: reef-ops | D69: Decide where the last boat money goes | E69: Leader | F69: S | G69: 30 | H69: $ | I69: Open | J69: Online | L69: 2 | M69: Good for you if you can make a hard call with little money | N69: Reef Ops has money for about 12 more boat days but needs about 45. Which sites get surveyed first decides whether the model learns all classes. | O69: 1. Count scored sites per class 2. List remaining sites by cost and class 3. Choose the next 12 boat days 4. Publish the choice | P69: A 12-day site plan with reasons | Q69: The plan raises the smallest class's count the most per dollar | R69: 2 Checkers review the counts | S69: Computes cost per class per site | T69: Makes the call, including weather and safety | U69: Site list, budget sheet | V69: Survey leadership | W69: r6 | X69: Spend on Cebu (cheap, many healthy sites) or Fiji (costly, bleached sites we lack)? | Y69: Cebu: more sites per dollar | Fiji: fill the missing class | Half and half
A70: r4 | B70: reef | C70: reef-ops | D70: Find a dive shop in Fiji to join us | E70: Planner | F70: S | G70: 25 | H70: $ | I70: Open | J70: Online | L70: 2 | M70: Good for you if you're good at cold emails | N70: Fiji has the bleached sites we lack. A local shop with trained divers cuts the cost of flying people in. | O70: 1. List 5 dive shops near the Fiji sites 2. Ask about at-cost boat days and survey training 3. Check their safety record and licences 4. Propose one | P70: Shortlist with replies and a recommended partner | Q70: One shop agrees in writing to a price per boat day | R70: Mission creator reads the written offer | S70: Finds shops and drafts emails | T70: Builds trust and negotiates | U70: Email, map | V70: Negotiation | W70: r7
A71: r1 | B71: reef | C71: reef-ops | D71: Dive and score 5 reefs near Cebu | E71: Expert | F71: L | G71: 250 | H71: $ | I71: Open | J71: On ground | K71: Certified divers only. Always dive with a buddy. Max 18 m, licensed local operator, dive insurance, no dive in bad weather. Touch nothing. | L71: 2 | M71: Good for you if you're a certified diver in Cebu | N71: Each site gives a 50 m transect and 20 photo-quadrats, timed within 30 days of a cloud-free satellite image. | O71: 1. Confirm permits and weather 2. Lay the transect at each site and photograph 20 quadrats 3. Record GPS, depth, time and the colour-chart score 4. Upload photos the same day | P71: 5 site reports with 100 photos and GPS | Q71: A Checker passes all 5 against the guide | R71: 1 marine-biology Checker reviews all photos | S71: Plans the route, checks the satellite pass dates and pre-fills forms | T71: Dives safely and scores the reef | U71: Underwater camera, quadrat frame, transect tape, slate, GPS | V71: Advanced dive certification, reef ID | W71: r11, r7 | X71: Visibility is 4 m at site 3. Your photos will be poor. | Y71: Score anyway and flag it | Skip and come back | Swap to a nearby backup site
A72: r8 | B72: reef | C72: reef-ops | D72: Snorkel-check 3 shallow reef flats in Bohol | E72: User | F72: M | G72: 50 | H72: $ | I72: Open | J72: On ground | K72: Snorkel only at low tide on flats under 3 m, with a buddy and a local guide. Wear reef shoes and a rash guard; never stand on coral. Check tide and weather first. | L72: 2 | M72: Good for you if you swim well and live near Bohol | N72: Reef flats are shallow enough to survey without a boat. It's cheaper and anyone who swims well can help. | O72: 1. Get the snorkel version of the guide 2. Swim a 20 m line and take 10 photos straight down 3. Hold the colour chart next to 5 corals 4. Log GPS from your phone in a waterproof pouch | P72: 3 site forms with 30 photos and GPS | Q72: A Checker passes at least 2 of 3 | R72: 1 Checker reviews all photos | S72: Picks the low-tide window and pre-fills forms | T72: Swims, photographs and scores | U72: Phone in pouch, Coral Health Chart | V72: Confident swimmer | W72: r11
A73: r2 | B73: reef | C73: reef-ops | D73: Check 30 dive reports against their photos | E73: Checker | F73: S | G73: 30 | H73: $ | I73: Open | J73: Online | L73: 2 | M73: Good for you if you can tell coral from algae in a photo | N73: 30 reports are waiting. Unchecked reports can't train the model, so this is the bottleneck right now. | O73: 1. Open each report and its photos 2. Check the score against the guide 3. Check GPS and date match 4. Pass, fix or reject | P73: 30 decisions with notes | Q73: All 30 decided; a second Checker agrees on 5 of 5 random picks | R73: A second Checker re-checks 5 | S73: Lines up photos with scores and flags mismatches | T73: Judges coral health from photos | U73: Report viewer, scoring guide | V73: Reef ID from photos | W73: r1, r8 | X73: A report's photos look right, but its GPS puts the site 400 m from the reef edge | Y73: Reject and ask the diver | Pass with the GPS corrected from the dive log | Pass, but keep it out of training
